Workbook

Sheet Master
A1: UOP | B1: Comitente | C1: Descripción UOP | D1: Sub Rubro | E1: Cert Nro | F1: Concepto | G1: Concepto Agrupado | H1: Período | I1: Anticipo Desacopiado ($) | J1: Importe Certificado | K1: Importe a facturar | L1: Estado Validación por insp. | M1: Tipo | N1: N° Comprobante | O1: Fecha Factura | P1: Concepto / Descripción | Q1: Anulada | R1: NC | S1: Importe Neto Factura | T1: IVA 10,05 | U1: IVA 21% | V1: Perp IVA | W1: IIBB Bs As ($) | X1: IIBB CABA ($) | Y1: IIBB Tucuman($) | Z1: IIBB Sta Fe ($) | AA1: Importe de factura ($) | AB1: Fecha Pago 1 | AC1: Monto Pago 1 ($) | AD1: Fecha Pago 2 | AE1: Monto Pago 2 ($) | AF1: Fecha Pago 3+ | AG1: Monto Pago 3+ ($) | AH1: Ret ganancias | AI1: Total Cobrado ($) | AJ1: Saldo ($) | AK1: Demora Pago (días)
A2: 00-121 | B2: DEPOSITO SAN PEDRO Y TALLER CENTRAL | C2: DEPOSITO SAN PEDRO Y TALLER CENTRAL | D2: DEPOSITO SAN PEDRO Y TALLER CENTRAL | E2: NA | F2: NA | G2: NA | H2: NA | J2: 4365000 | K2: 4365000 | L2: Validado | M2: FC A | N2: 2566 | O2: 46038 | P2: Por el alquiler de 5 (cinco) días de excavadora con operador (Corresponde a U$S 3.000,00.- al tipo de cambio vendedor BN | Q2: NO | R2: N/A | S2: =+J2 | U2: =+S2*21% | V2: =+S2*3% | W2: =+S2*1.5% | X2: =IF(A2="00-175",S2*0.06,0) | AA2: =+S2+T2+U2+W2+X2+V2+Y2 | AB2: 46045 | AC2: 5216847 | AH2: 261228 | AI2: =+AC2+AE2+AG2+AH2 | AJ2: =+AA2-AI2 | AK2: =IF(Q2="ANULADA","N/A",IF(ABS(AJ2)>10,"Pendiente",IF(MAX(AB2,AD2,AF2)=0,"Pendiente",MAX(0,MAX(AB2,AD2,AF2)-O2))))
A3: 00-172 | B3: NUEVA MARINAS DE HUDSON INVERSORA SA | C3: Rotondas PN | D3: Rotondas PN | E3: 4 | F3: Cartificado Coste y Costas N4 | G3: Rotondas PN | H3: 45778 | J3: 23513374 | K3: 23513374 | L3: Validado | M3: FC A | N3: 2485 | O3: 45848 | P3: Cartificado Coste y Costas N4 | Q3: NO | R3: N/A | S3: =+J3 | U3: =+S3*21% | V3: =+S3*3% | W3: =+S3*2.5% | X3: =IF(A3="00-175",S3*0.06,0) | AA3: =+S3+T3+U3+W3+X3+V3+Y3 | AB3: 46219 | AC3: 29744418 | AI3: =+AC3+AE3+AG3+AH3 | AJ3: =+AA3-AI3 | AK3: =IF(Q3="ANULADA","N/A",IF(ABS(AJ3)>10,"Pendiente",IF(MAX(AB3,AD3,AF3)=0,"Pendiente",MAX(0,MAX(AB3,AD3,AF3)-O3))))
A4: 00-172 | B4: NUEVA MARINAS DE HUDSON INVERSORA SA | C4: Rotondas PN | D4: Rotondas PN | E4: 1 | F4: Certificado Nº 1 - May'25.. | G4: Rotondas PN | H4: 45778 | J4: 30876813 | K4: 30876813 | L4: Validado | M4: FC A | N4: 2486 | O4: 45848 | P4: Certificado Nº 1 - May'25.. | Q4: NO | R4: N/A | S4: =+J4 | U4: =+S4*21% | V4: =+S4*3% | W4: =+S4*2.5% | X4: =IF(A4="00-175",S4*0.06,0) | AA4: =+S4+T4+U4+W4+X4+V4+Y4 | AB4: 46219 | AC4: 39059169 | AI4: =+AC4+AE4+AG4+AH4 | AJ4: =+AA4-AI4 | AK4: =IF(Q4="ANULADA","N/A",IF(ABS(AJ4)>10,"Pendiente",IF(MAX(AB4,AD4,AF4)=0,"Pendiente",MAX(0,MAX(AB4,AD4,AF4)-O4))))
A5: 00-173 | B5: FIDEICOMISO MARINAS DEL PLATA | C5: EDIFICIOS MD 2 y 3 (Pto. NIZUC) | D5: Agua Tratada YPF | F5: Agua Tratada YPF | G5: Agua Tratada YPF | H5: NA | J5: 76100794 | K5: 76100794 | L5: Validado | M5: FC A | N5: 2483 | O5: 45833 | P5: Trabajos de Agua Tratada Planta YPF a Canal Exterior Puerto Nizuc. - EDIFICIOS MD 2 y 3 (Pto. NIZUC) (00173) | Q5: NO | R5: N/A | S5: =+J5 | U5: =+S5*21% | V5: =+S5*3% | W5: =+S5*2.5% | X5: =IF(A5="00-175",S5*0.06,0) | AA5: =+S5+T5+U5+W5+X5+V5+Y5 | AB5: 45839 | AC5: =AA5-AH5 | AH5: 2357473.6 | AI5: =+AC5+AE5+AG5+AH5 | AJ5: =+AA5-AI5 | AK5: =IF(Q5="ANULADA","N/A",IF(ABS(AJ5)>10,"Pendiente",IF(MAX(AB5,AD5,AF5)=0,"Pendiente",MAX(0,MAX(AB5,AD5,AF5)-O5))))
A6: 00-173 | B6: FIDEICOMISO MARINAS DEL PLATA | C6: EDIFICIOS MD 2 y 3 (Pto. NIZUC) | G6: Básico | H6: 45717 | J6: 1.5402088e+08 | K6: 1.5402088e+08 | M6: FC A | N6: 2517 | O6: 45946 | P6: Certificado Básico Nº 1 - Mar'25.. - EDIFICIOS MD 2 y 3 (Pto. NIZUC) (00173) | Q6: ANULADA | R6: 344 | S6: =+J6 | U6: =+S6*21% | V6: =+S6*3% | W6: =+S6*2.5% | X6: =IF(A6="00-175",S6*0.06,0) | AA6: =+S6+T6+U6+W6+X6+V6+Y6 | AI6: =+AC6+AE6+AG6+AH6 | AJ6: =+AA6-AI6 | AK6: =IF(Q6="ANULADA","N/A",IF(ABS(AJ6)>10,"Pendiente",IF(MAX(AB6,AD6,AF6)=0,"Pendiente",MAX(0,MAX(AB6,AD6,AF6)-O6))))
A7: 00-173 | B7: FIDEICOMISO MARINAS DEL PLATA | C7: EDIFICIOS MD 2 y 3 (Pto. NIZUC) | G7: Básico | H7: 45748 | J7: 87443208 | K7: 87443208 | M7: FC A | N7: 2518 | O7: 45946 | P7: Certificado Básico Nº 2 - Abr'25. - EDIFICIOS MD 2 y 3 (Pto. NIZUC) (00173) | Q7: ANULADA | R7: 345 | S7: =+J7 | U7: =+S7*21% | V7: =+S7*3% | W7: =+S7*2.5% | X7: =IF(A7="00-175",S7*0.06,0) | AA7: =+S7+T7+U7+W7+X7+V7+Y7 | AI7: =+AC7+AE7+AG7+AH7 | AJ7: =+AA7-AI7 | AK7: =IF(Q7="ANULADA","N/A",IF(ABS(AJ7)>10,"Pendiente",IF(MAX(AB7,AD7,AF7)=0,"Pendiente",MAX(0,MAX(AB7,AD7,AF7)-O7))))
A8: 00-173 | B8: FIDEICOMISO MARINAS DEL PLATA | C8: EDIFICIOS MD 2 y 3 (Pto. NIZUC) | G8: Básico | H8: 45778 | J8: 1.051615e+08 | K8: 1.051615e+08 | M8: FC A | N8: 2519 | O8: 45946 | P8: Certificado Básico Nº 3 - May'25.. - EDIFICIOS MD 2 y 3 (Pto. NIZUC) (00173) | Q8: ANULADA | R8: 346 | S8: =+J8 | U8: =+S8*21% | V8: =+S8*3% | W8: =+S8*2.5% | X8: =IF(A8="00-175",S8*0.06,0) | AA8: =+S8+T8+U8+W8+X8+V8+Y8 | AI8: =+AC8+AE8+AG8+AH8 | AJ8: =+AA8-AI8 | AK8: =IF(Q8="ANULADA","N/A",IF(ABS(AJ8)>10,"Pendiente",IF(MAX(AB8,AD8,AF8)=0,"Pendiente",MAX(0,MAX(AB8,AD8,AF8)-O8))))
A9: 00-173 | B9: FIDEICOMISO MARINAS DEL PLATA | C9: EDIFICIOS MD 2 y 3 (Pto. NIZUC) | G9: Básico | H9: 45809 | J9: 1.0509594e+08 | K9: 1.0509594e+08 | M9: FC A | N9: 2520 | O9: 45946 | P9: Certificado Básico Nº 4 - Jun'25. - EDIFICIOS MD 2 y 3 (Pto. NIZUC) (00173) | Q9: ANULADA | R9: 347 | S9: =+J9 | U9: =+S9*21% | V9: =+S9*3% | W9: =+S9*2.5% | X9: =IF(A9="00-175",S9*0.06,0) | AA9: =+S9+T9+U9+W9+X9+V9+Y9 | AI9: =+AC9+AE9+AG9+AH9 | AJ9: =+AA9-AI9 | AK9: =IF(Q9="ANULADA","N/A",IF(ABS(AJ9)>10,"Pendiente",IF(MAX(AB9,AD9,AF9)=0,"Pendiente",MAX(0,MAX(AB9,AD9,AF9)-O9))))
A10: 00-173 | B10: FIDEICOMISO MARINAS DEL PLATA | C10: EDIFICIOS MD 2 y 3 (Pto. NIZUC) | G10: Básico | H10: 45839 | J10: 1.0753981e+08 | K10: 1.0753981e+08 | M10: FC A | N10: 2521 | O10: 45946 | P10: Certificado Básico Nº 5 - Jul'25.. - EDIFICIOS MD 2 y 3 (Pto. NIZUC) (00173) | Q10: ANULADA | R10: 348 | S10: =+J10 | U10: =+S10*21% | V10: =+S10*3% | W10: =+S10*2.5% | X10: =IF(A10="00-175",S10*0.06,0) | AA10: =+S10+T10+U10+W10+X10+V10+Y10 | AI10: =+AC10+AE10+AG10+AH10 | AJ10: =+AA10-AI10 | AK10: =IF(Q10="ANULADA","N/A",IF(ABS(AJ10)>10,"Pendiente",IF(MAX(AB10,AD10,AF10)=0,"Pendiente",MAX(0,MAX(AB10,AD10,AF10)-O10))))
A11: 00-173 | B11: FIDEICOMISO MARINAS DEL PLATA | C11: EDIFICIOS MD 2 y 3 (Pto. NIZUC) | G11: Básico | H11: 45870 | J11: 1.0337725e+08 | K11: 1.0337725e+08 | M11: FC A | N11: 2522 | O11: 45946 | P11: Certificado Básico Nº 6 - Ago'25. - EDIFICIOS MD 2 y 3 (Pto. NIZUC) (00173) | Q11: ANULADA | R11: 349 | S11: =+J11 | U11: =+S11*21% | V11: =+S11*3% | W11: =+S11*2.5% | X11: =IF(A11="00-175",S11*0.06,0) | AA11: =+S11+T11+U11+W11+X11+V11+Y11 | AI11: =+AC11+AE11+AG11+AH11 | AJ11: =+AA11-AI11 | AK11: =IF(Q11="ANULADA","N/A",IF(ABS(AJ11)>10,"Pendiente",IF(MAX(AB11,AD11,AF11)=0,"Pendiente",MAX(0,MAX(AB11,AD11,AF11)-O11))))
A12: 00-173 | B12: FIDEICOMISO MARINAS DEL PLATA | C12: EDIFICIOS MD 2 y 3 (Pto. NIZUC) | G12: Redet. | H12: 45717 | J12: 26183550 | K12: 26183550 | M12: FC A | N12: 2523 | O12: 45946 | P12: Certificado Redeterminado Básico Nº 1 - Mar'25. - EDIFICIOS MD 2 y 3 (Pto. NIZUC) (00173) | Q12: ANULADA | R12: 350 | S12: =+J12 | U12: =+S12*21% | V12: =+S12*3% | W12: =+S12*2.5% | X12: =IF(A12="00-175",S12*0.06,0) | AA12: =+S12+T12+U12+W12+X12+V12+Y12 | AI12: =+AC12+AE12+AG12+AH12 | AJ12: =+AA12-AI12 | AK12: =IF(Q12="ANULADA","N/A",IF(ABS(AJ12)>10,"Pendiente",IF(MAX(AB12,AD12,AF12)=0,"Pendiente",MAX(0,MAX(AB12,AD12,AF12)-O12))))
A13: 00-173 | B13: FIDEICOMISO MARINAS DEL PLATA | C13: EDIFICIOS MD 2 y 3 (Pto. NIZUC) | G13: Redet. | H13: 45748 | J13: 17642182 | K13: 17642182 | M13: FC A | N13: 2524 | O13: 45946 | P13: Certificado Redeterminado Básico Nº 2 - Abr'25. - EDIFICIOS MD 2 y 3 (Pto. NIZUC) (00173) | Q13: ANULADA | R13: 351 | S13: =+J13 | U13: =+S13*21% | V13: =+S13*3% | W13: =+S13*2.5% | X13: =IF(A13="00-175",S13*0.06,0) | AA13: =+S13+T13+U13+W13+X13+V13+Y13 | AI13: =+AC13+AE13+AG13+AH13 | AJ13: =+AA13-AI13 | AK13: =IF(Q13="ANULADA","N/A",IF(ABS(AJ13)>10,"Pendiente",IF(MAX(AB13,AD13,AF13)=0,"Pendiente",MAX(0,MAX(AB13,AD13,AF13)-O13))))
A14: 00-173 | B14: FIDEICOMISO MARINAS DEL PLATA | C14: EDIFICIOS MD 2 y 3 (Pto. NIZUC) | G14: Redet. | H14: 45809 | J14: 29083534 | K14: 29083534 | M14: FC A | N14: 2525 | O14: 45946 | P14: Certificado Redeterminado Básico Nº 4 - Jun'25.. - EDIFICIOS MD 2 y 3 (Pto. NIZUC) (00173) | Q14: ANULADA | R14: 352 | S14: =+J14 | U14: =+S14*21% | V14: =+S14*3% | W14: =+S14*2.5% | X14: =IF(A14="00-175",S14*0.06,0) | AA14: =+S14+T14+U14+W14+X14+V14+Y14 | AI14: =+AC14+AE14+AG14+AH14 | AJ14: =+AA14-AI14 | AK14: =IF(Q14="ANULADA","N/A",IF(ABS(AJ14)>10,"Pendiente",IF(MAX(AB14,AD14,AF14)=0,"Pendiente",MAX(0,MAX(AB14,AD14,AF14)-O14))))
A15: 00-173 | B15: FIDEICOMISO MARINAS DEL PLATA | C15: EDIFICIOS MD 2 y 3 (Pto. NIZUC) | G15: Redet. | H15: 45778 | J15: 16929640 | K15: 16929640 | M15: FC A | N15: 2526 | O15: 45946 | P15: Certificado Redeterminado Básico Nº 3 - May'25.. - EDIFICIOS MD 2 y 3 (Pto. NIZUC) (00173) | Q15: ANULADA | R15: 353 | S15: =+J15 | U15: =+S15*21% | V15: =+S15*3% | W15: =+S15*2.5% | X15: =IF(A15="00-175",S15*0.06,0) | AA15: =+S15+T15+U15+W15+X15+V15+Y15 | AI15: =+AC15+AE15+AG15+AH15 | AJ15: =+AA15-AI15 | AK15: =IF(Q15="ANULADA","N/A",IF(ABS(AJ15)>10,"Pendiente",IF(MAX(AB15,AD15,AF15)=0,"Pendiente",MAX(0,MAX(AB15,AD15,AF15)-O15))))
A16: 00-173 | B16: FIDEICOMISO MARINAS DEL PLATA | C16: EDIFICIOS MD 2 y 3 (Pto. NIZUC) | G16: Redet. | H16: 45839 | J16: 26140242 | K16: 26140242 | M16: FC A | N16: 2527 | O16: 45946 | P16: Certificado Redeterminado Básico Nº 5 - Jul'25.. - EDIFICIOS MD 2 y 3 (Pto. NIZUC) (00173) | Q16: ANULADA | R16: 354 | S16: =+J16 | U16: =+S16*21% | V16: =+S16*3% | W16: =+S16*2.5% | X16: =IF(A16="00-175",S16*0.06,0) | AA16: =+S16+T16+U16+W16+X16+V16+Y16 | AI16: =+AC16+AE16+AG16+AH16 | AJ16: =+AA16-AI16 | AK16: =IF(Q16="ANULADA","N/A",IF(ABS(AJ16)>10,"Pendiente",IF(MAX(AB16,AD16,AF16)=0,"Pendiente",MAX(0,MAX(AB16,AD16,AF16)-O16))))
A17: 00-173 | B17: FIDEICOMISO MARINAS DEL PLATA | C17: EDIFICIOS MD 2 y 3 (Pto. NIZUC) | G17: Redet. | H17: 45870 | J17: 29337902 | K17: 29337902 | M17: FC A | N17: 2528 | O17: 45946 | P17: Certificado Redeterminado Básico Nº 6 - Ago'25.. - EDIFICIOS MD 2 y 3 (Pto. NIZUC) (00173) | Q17: ANULADA | R17: 355 | S17: =+J17 | U17: =+S17*21% | V17: =+S17*3% | W17: =+S17*2.5% | X17: =IF(A17="00-175",S17*0.06,0) | AA17: =+S17+T17+U17+W17+X17+V17+Y17 | AI17: =+AC17+AE17+AG17+AH17 | AJ17: =+AA17-AI17 | AK17: =IF(Q17="ANULADA","N/A",IF(ABS(AJ17)>10,"Pendiente",IF(MAX(AB17,AD17,AF17)=0,"Pendiente",MAX(0,MAX(AB17,AD17,AF17)-O17))))
... A23: 00-173 | B23: FIDEICOMISO MARINAS DEL PLATA | C23: EDIFICIOS MD 2 y 3 (Pto. NIZUC) | G23: Básico | H23: 45870 | J23: 1.9255204e+08 | K23: 1.9255204e+08 | M23: FC A | N23: 2534 | O23: 45946 | P23: Certificado Costes y Costas Nº 6 - Ago'25. - EDIFICIOS MD 2 y 3 (Pto. NIZUC) (00173) | Q23: ANULADA | R23: 361 | S23: =+J23 | U23: =+S23*21% | V23: =+S23*3% | W23: =+S23*2.5% | X23: =IF(A23="00-175",S23*0.06,0) | AA23: =+S23+T23+U23+W23+X23+V23+Y23 | AI23: =+AC23+AE23+AG23+AH23 | AJ23: =+AA23-AI23 | AK23: =IF(Q23="ANULADA","N/A",IF(ABS(AJ23)>10,"Pendiente",IF(MAX(AB23,AD23,AF23)=0,"Pendiente",MAX(0,MAX(AB23,AD23,AF23)-O23))))
A24: 00-175 | B24: NUEVA MARINAS DE HUDSON INVERSORA SA | C24: Laguna 4 - Puerto Nizuc | D24: Laguna 4 | E24: 1 | F24: Basico | G24: Básico | H24: 45778 | J24: 23489775 | K24: 23489775 | L24: Validado | M24: FC A | N24: 2488 | O24: 45848 | P24: Certificado Nº 1 - May'25.. - Laguna 4 - Puerto Nizuc (00175) | Q24: NO | R24: N/A | S24: =+J24 | U24: =+S24*21% | V24: =+S24*3% | W24: =+S24*0.3% | X24: =IF(A24="00-175",S24*0.06,0) | AA24: =+S24+T24+U24+W24+X24+V24+Y24 | AB24: 45861 | AC24: 30607177 | AI24: =+AC24+AE24+AG24+AH24 | AJ24: =+AA24-AI24 | AK24: =IF(Q24="ANULADA","N/A",IF(ABS(AJ24)>10,"Pendiente",IF(MAX(AB24,AD24,AF24)=0,"Pendiente",MAX(0,MAX(AB24,AD24,AF24)-O24))))
A25: 00-175 | B25: NUEVA MARINAS DE HUDSON INVERSORA SA | C25: Laguna 4 - Puerto Nizuc | D25: Laguna 4 | E25: 1 | F25: Basico | G25: Básico | H25: 45778 | J25: 86901861 | K25: 86901861 | L25: Validado | M25: FC A | N25: 2490 | O25: 45882 | P25: Certificado Nº 1 - May'25. - Laguna 4 - Puerto Nizuc (00175) | Q25: NO | R25: N/A | S25: =+J25 | U25: =+S25*21% | V25: =+S25*3% | W25: =+S25*0.3% | X25: =IF(A25="00-175",S25*0.06,0) | AA25: =+S25+T25+U25+W25+X25+V25+Y25 | AB25: 45909 | AC25: 1.1323312e+08 | AI25: =+AC25+AE25+AG25+AH25 | AJ25: =+AA25-AI25 | AK25: =IF(Q25="ANULADA","N/A",IF(ABS(AJ25)>10,"Pendiente",IF(MAX(AB25,AD25,AF25)=0,"Pendiente",MAX(0,MAX(AB25,AD25,AF25)-O25))))
A26: 00-175 | B26: NUEVA MARINAS DE HUDSON INVERSORA SA | C26: Laguna 4 - Puerto Nizuc | D26: Laguna 4 | E26: 1 | F26: Redet | G26: Redet. | H26: 45778 | J26: 4206050.1 | K26: 4206050.1 | L26: Validado | M26: FC A | N26: 2491 | O26: 45882 | P26: Certificado de Redeterminación Provisoria Nº 1 - May'25. - Laguna 4 - Puerto Nizuc (00175) | Q26: NO | R26: N/A | S26: =+J26 | U26: =+S26*21% | V26: =+S26*3% | W26: =+S26*0.3% | X26: =IF(A26="00-175",S26*0.06,0) | AA26: =+S26+T26+U26+W26+X26+V26+Y26 | AB26: 45909 | AC26: 5480483.2 | AI26: =+AC26+AE26+AG26+AH26 | AJ26: =+AA26-AI26 | AK26: =IF(Q26="ANULADA","N/A",IF(ABS(AJ26)>10,"Pendiente",IF(MAX(AB26,AD26,AF26)=0,"Pendiente",MAX(0,MAX(AB26,AD26,AF26)-O26))))
A27: 00-175 | B27: NUEVA MARINAS DE HUDSON INVERSORA SA | C27: Laguna 4 - Puerto Nizuc | D27: Laguna 4 | E27: 2 | F27: Basico | G27: Básico | H27: 45809 | J27: 85346702 | K27: 85346702 | L27: Validado | M27: FC A | N27: 2494 | O27: 45896 | P27: Certificado Nº 2 - Jun'25.. - Laguna 4 - Puerto Nizuc (00175) | Q27: NO | R27: N/A | S27: =+J27 | U27: =+S27*21% | V27: =+S27*3% | W27: =+S27*0.3% | X27: =IF(A27="00-175",S27*0.06,0) | AA27: =+S27+T27+U27+W27+X27+V27+Y27 | AB27: 45909 | AC27: 1.1120675e+08 | AI27: =+AC27+AE27+AG27+AH27 | AJ27: =+AA27-AI27 | AK27: =IF(Q27="ANULADA","N/A",IF(ABS(AJ27)>10,"Pendiente",IF(MAX(AB27,AD27,AF27)=0,"Pendiente",MAX(0,MAX(AB27,AD27,AF27)-O27))))
A28: 00-175 | B28: NUEVA MARINAS DE HUDSON INVERSORA SA | C28: Laguna 4 - Puerto Nizuc | D28: Laguna 4 | E28: 2 | F28: Redet | G28: Redet. | H28: 45809 | J28: 7110680.5 | K28: 7110680.5 | L28: Validado | M28: FC A | N28: 2495 | O28: 45896 | P28: Certificado de Redeterminación Provisoria Nº 2 - Jun'25. - Laguna 4 - Puerto Nizuc (00175) | Q28: NO | R28: N/A | S28: =+J28 | U28: =+S28*21% | V28: =+S28*3% | W28: =+S28*0.3% | X28: =IF(A28="00-175",S28*0.06,0) | AA28: =+S28+T28+U28+W28+X28+V28+Y28 | AB28: 45926 | AC28: 9265216.7 | AI28: =+AC28+AE28+AG28+AH28 | AJ28: =+AA28-AI28 | AK28: =IF(Q28="ANULADA","N/A",IF(ABS(AJ28)>10,"Pendiente",IF(MAX(AB28,AD28,AF28)=0,"Pendiente",MAX(0,MAX(AB28,AD28,AF28)-O28))))
A29: 00-175 | B29: NUEVA MARINAS DE HUDSON INVERSORA SA | C29: Laguna 4 - Puerto Nizuc | D29: Laguna 4 | E29: 2 | F29: Basico | G29: Básico | H29: 45809 | J29: 51931236 | K29: 51931236 | L29: Validado | M29: FC A | N29: 2499 | O29: 45897 | P29: Certificado Nº 2 - Jun'25.. - Laguna 4 - Puerto Nizuc (00175) | Q29: NO | R29: N/A | S29: =+J29 | U29: =+S29*21% | V29: =+S29*3% | W29: =+S29*0.3% | X29: =IF(A29="00-175",S29*0.06,0) | AA29: =+S29+T29+U29+W29+X29+V29+Y29 | AB29: 45917 | AC29: 67666400 | AI29: =+AC29+AE29+AG29+AH29 | AJ29: =+AA29-AI29 | AK29: =IF(Q29="ANULADA","N/A",IF(ABS(AJ29)>10,"Pendiente",IF(MAX(AB29,AD29,AF29)=0,"Pendiente",MAX(0,MAX(AB29,AD29,AF29)-O29))))
A30: 00-175 | B30: NUEVA MARINAS DE HUDSON INVERSORA SA | C30: Laguna 4 - Puerto Nizuc | D30: Laguna 4 | E30: 2 | F30: Redet | G30: Redet. | H30: 45809 | J30: 1244446.7 | K30: 1244446.7 | L30: Validado | M30: FC A | N30: 2500 | O30: 45897 | P30: Certificado de Redeterminación Provisoria Nº 2 - Jun'25. - Laguna 4 - Puerto Nizuc (00175) | Q30: NO | R30: N/A | S30: =+J30 | U30: =+S30*21% | V30: =+S30*3% | W30: =+S30*0.3% | X30: =IF(A30="00-175",S30*0.06,0) | AA30: =+S30+T30+U30+W30+X30+V30+Y30 | AB30: 45917 | AC30: 1621514 | AI30: =+AC30+AE30+AG30+AH30 | AJ30: =+AA30-AI30 | AK30: =IF(Q30="ANULADA","N/A",IF(ABS(AJ30)>10,"Pendiente",IF(MAX(AB30,AD30,AF30)=0,"Pendiente",MAX(0,MAX(AB30,AD30,AF30)-O30))))
A31: 00-175 | B31: NUEVA MARINAS DE HUDSON INVERSORA SA | C31: Laguna 4 - Puerto Nizuc | D31: Laguna 4 | E31: 3 | F31: Basico | G31: Básico | H31: 45839 | J31: 1.3022096e+08 | K31: 1.3022096e+08 | L31: Validado | M31: FC A | N31: 2504 | O31: 45903 | P31: Certificado Nº 3 - Jul'25.. - Laguna 4 - Puerto Nizuc (00175) | Q31: NO | R31: N/A | S31: =+J31 | U31: =+S31*21% | V31: =+S31*3% | W31: =+S31*0.3% | X31: =IF(A31="00-175",S31*0.06,0) | AA31: =+S31+T31+U31+W31+X31+V31+Y31 | AB31: 45926 | AC31: 1.6967792e+08 | AI31: =+AC31+AE31+AG31+AH31 | AJ31: =+AA31-AI31 | AK31: =IF(Q31="ANULADA","N/A",IF(ABS(AJ31)>10,"Pendiente",IF(MAX(AB31,AD31,AF31)=0,"Pendiente",MAX(0,MAX(AB31,AD31,AF31)-O31))))
A32: 00-175 | B32: NUEVA MARINAS DE HUDSON INVERSORA SA | C32: Laguna 4 - Puerto Nizuc | D32: Laguna 4 | E32: 3 | F32: Redet | G32: Redet. | H32: 45839 | J32: 10236945 | K32: 10236945 | L32: Validado | M32: FC A | N32: 2505 | O32: 45903 | P32: Certificado de Redeterminación Provisoria Nº 3 - Jul'25. - Laguna 4 - Puerto Nizuc (00175) | Q32: NO | R32: N/A | S32: =+J32 | U32: =+S32*21% | V32: =+S32*3% | W32: =+S32*0.3% | X32: =IF(A32="00-175",S32*0.06,0) | AA32: =+S32+T32+U32+W32+X32+V32+Y32 | AB32: 45926 | AC32: 13338740 | AI32: =+AC32+AE32+AG32+AH32 | AJ32: =+AA32-AI32 | AK32: =IF(Q32="ANULADA","N/A",IF(ABS(AJ32)>10,"Pendiente",IF(MAX(AB32,AD32,AF32)=0,"Pendiente",MAX(0,MAX(AB32,AD32,AF32)-O32))))
A33: 00-175 | B33: NUEVA MARINAS DE HUDSON INVERSORA SA | C33: Laguna 4 - Puerto Nizuc | D33: Laguna 4 | E33: 3 | F33: Basico | G33: Básico | H33: 45839 | J33: 11131246 | K33: 11131246 | L33: Validado | M33: FC A | N33: 2506 | O33: 45903 | P33: Certificado Nº 3 - Jul'25.. - Laguna 4 - Puerto Nizuc (00175) | Q33: NO | R33: N/A | S33: =+J33 | U33: =+S33*21% | V33: =+S33*3% | W33: =+S33*0.3% | X33: =IF(A33="00-175",S33*0.06,0) | AA33: =+S33+T33+U33+W33+X33+V33+Y33 | AB33: 45917 | AC33: 14504014 | AI33: =+AC33+AE33+AG33+AH33 | AJ33: =+AA33-AI33 | AK33: =IF(Q33="ANULADA","N/A",IF(ABS(AJ33)>10,"Pendiente",IF(MAX(AB33,AD33,AF33)=0,"Pendiente",MAX(0,MAX(AB33,AD33,AF33)-O33))))
A34: 00-175 | B34: NUEVA MARINAS DE HUDSON INVERSORA SA | C34: Laguna 4 - Puerto Nizuc | D34: Laguna 4 | E34: 3 | F34: Redet | G34: Redet. | H34: 45839 | J34: 656634.16 | K34: 656634.16 | L34: Validado | M34: FC A | N34: 2507 | O34: 45903 | P34: Certificado de Redeterminación Provisoria Nº 3 - Jul'25. - Laguna 4 - Puerto Nizuc (00175) | Q34: NO | R34: N/A | S34: =+J34 | U34: =+S34*21% | V34: =+S34*3% | W34: =+S34*0.3% | X34: =IF(A34="00-175",S34*0.06,0) | AA34: =+S34+T34+U34+W34+X34+V34+Y34 | AB34: 45917 | AC34: 855594.31 | AI34: =+AC34+AE34+AG34+AH34 | AJ34: =+AA34-AI34 | AK34: =IF(Q34="ANULADA","N/A",IF(ABS(AJ34)>10,"Pendiente",IF(MAX(AB34,AD34,AF34)=0,"Pendiente",MAX(0,MAX(AB34,AD34,AF34)-O34))))
A35: 00-175 | B35: NUEVA MARINAS DE HUDSON INVERSORA SA | C35: Laguna 4 - Puerto Nizuc | D35: Laguna 4 | E35: 4 | F35: Basico | G35: Básico | H35: 45870 | J35: 1.3151263e+08 | K35: 1.3151263e+08 | L35: Validado | M35: FC A | N35: 2509 | O35: 45915 | P35: Certificado Nº 4 - Ago'25. - Laguna 4 - Puerto Nizuc (00175) | Q35: NO | R35: N/A | S35: =+J35 | U35: =+S35*21% | V35: =+S35*3% | W35: =+S35*0.3% | X35: =IF(A35="00-175",S35*0.06,0) | AA35: =+S35+T35+U35+W35+X35+V35+Y35 | AB35: 45959 | AC35: 19283383 | AD35: 45987 | AE35: 1.5207758e+08 | AI35: =+AC35+AE35+AG35+AH35 | AJ35: =+AA35-AI35 | AK35: =IF(Q35="ANULADA","N/A",IF(ABS(AJ35)>10,"Pendiente",IF(MAX(AB35,AD35,AF35)=0,"Pendiente",MAX(0,MAX(AB35,AD35,AF35)-O35))))
A36: 00-175 | B36: NUEVA MARINAS DE HUDSON INVERSORA SA | C36: Laguna 4 - Puerto Nizuc | D36: Laguna 4 | E36: 4 | F36: Redet | G36: Redet. | H36: 45870 | J36: 14665290 | K36: 14665290 | L36: Validado | M36: FC A | N36: 2510 | O36: 45915 | P36: Certificado de Redeterminación Provisoria Nº 4 - Ago'25. - Laguna 4 - Puerto Nizuc (00175) | Q36: NO | R36: N/A | S36: =+J36 | U36: =+S36*21% | V36: =+S36*3% | W36: =+S36*0.3% | X36: =IF(A36="00-175",S36*0.06,0) | AA36: =+S36+T36+U36+W36+X36+V36+Y36 | AB36: 45987 | AC36: 19108873 | AI36: =+AC36+AE36+AG36+AH36 | AJ36: =+AA36-AI36 | AK36: =IF(Q36="ANULADA","N/A",IF(ABS(AJ36)>10,"Pendiente",IF(MAX(AB36,AD36,AF36)=0,"Pendiente",MAX(0,MAX(AB36,AD36,AF36)-O36))))
A37: 00-175 | B37: NUEVA MARINAS DE HUDSON INVERSORA SA | C37: Laguna 4 - Puerto Nizuc | D37: Laguna 4 | E37: 4 | F37: Basico | G37: Básico | H37: 45870 | J37: 10560323 | K37: 10560323 | L37: Validado | M37: FC A | N37: 2511 | O37: 45915 | P37: Certificado Nº 4 - Ago'25. - Laguna 4 - Puerto Nizuc (00175) | Q37: NO | R37: N/A | S37: =+J37 | U37: =+S37*21% | V37: =+S37*3% | W37: =+S37*0.3% | X37: =IF(A37="00-175",S37*0.06,0) | AA37: =+S37+T37+U37+W37+X37+V37+Y37 | AB37: 45939 | AC37: 13760101 | AI37: =+AC37+AE37+AG37+AH37 | AJ37: =+AA37-AI37 | AK37: =IF(Q37="ANULADA","N/A",IF(ABS(AJ37)>10,"Pendiente",IF(MAX(AB37,AD37,AF37)=0,"Pendiente",MAX(0,MAX(AB37,AD37,AF37)-O37))))
A38: 00-175 | B38: NUEVA MARINAS DE HUDSON INVERSORA SA | C38: Laguna 4 - Puerto Nizuc | D38: Laguna 4 | E38: 4 | F38: Redet | G38: Redet. | H38: 45870 | J38: 648234.33 | K38: 648234.33 | L38: Validado | M38: FC A | N38: 2512 | O38: 45915 | P38: Certificado de Redeterminación Provisoria Nº 4 - Ago'25. - Laguna 4 - Puerto Nizuc (00175) | Q38: NO | R38: N/A | S38: =+J38 | U38: =+S38*21% | V38: =+S38*3% | W38: =+S38*0.3% | X38: =IF(A38="00-175",S38*0.06,0) | AA38: =+S38+T38+U38+W38+X38+V38+Y38 | AB38: 45939 | AC38: 844649.33 | AI38: =+AC38+AE38+AG38+AH38 | AJ38: =+AA38-AI38 | AK38: =IF(Q38="ANULADA","N/A",IF(ABS(AJ38)>10,"Pendiente",IF(MAX(AB38,AD38,AF38)=0,"Pendiente",MAX(0,MAX(AB38,AD38,AF38)-O38))))
A39: 00-175 | B39: NUEVA MARINAS DE HUDSON INVERSORA SA | C39: Laguna 4 - Puerto Nizuc | D39: Laguna 4 | E39: 5 | F39: Basico | G39: Básico | H39: 45901 | J39: 9000058.1 | K39: 9000058.1 | L39: Validado | M39: FC A | N39: 2535 | O39: 45947 | P39: Certificado Nº 5 - Sep'25 - Ensanche. - Laguna 4 - Puerto Nizuc (00175) | Q39: NO | R39: N/A | S39: =+J39 | U39: =+S39*21% | V39: =+S39*3% | W39: =+S39*0.3% | X39: =IF(A39="00-175",S39*0.06,0) | AA39: =+S39+T39+U39+W39+X39+V39+Y39 | AB39: 45988 | AC39: 11727076 | AI39: =+AC39+AE39+AG39+AH39 | AJ39: =+AA39-AI39 | AK39: =IF(Q39="ANULADA","N/A",IF(ABS(AJ39)>10,"Pendiente",IF(MAX(AB39,AD39,AF39)=0,"Pendiente",MAX(0,MAX(AB39,AD39,AF39)-O39))))
A40: 00-175 | B40: NUEVA MARINAS DE HUDSON INVERSORA SA | C40: Laguna 4 - Puerto Nizuc | D40: Laguna 4 | E40: 5 | F40: Redet | G40: Redet. | H40: 45901 | J40: 379802.46 | K40: 379802.46 | L40: Validado | M40: FC A | N40: 2536 | O40: 45947 | P40: Certificado de Redeterminación Provisoria Nº 5 - Sep'25 - Ensanche. - Laguna 4 - Puerto Nizuc (00175) | Q40: NO | R40: N/A | S40: =+J40 | U40: =+S40*21% | V40: =+S40*3% | W40: =+S40*0.3% | X40: =IF(A40="00-175",S40*0.06,0) | AA40: =+S40+T40+U40+W40+X40+V40+Y40 | AB40: 45988 | AC40: 494882.6 | AI40: =+AC40+AE40+AG40+AH40 | AJ40: =+AA40-AI40 | AK40: =IF(Q40="ANULADA","N/A",IF(ABS(AJ40)>10,"Pendiente",IF(MAX(AB40,AD40,AF40)=0,"Pendiente",MAX(0,MAX(AB40,AD40,AF40)-O40))))
A41: 00-175 | B41: NUEVA MARINAS DE HUDSON INVERSORA SA | C41: Laguna 4 - Puerto Nizuc | D41: Laguna 4 | E41: 5 | F41: Basico | G41: Básico | H41: 45901 | J41: 1.8224181e+08 | K41: 1.8224181e+08 | L41: Validado | M41: FC A | N41: 2538 | O41: 45952 | P41: Certificado Nº 5 - Sep'25.. - Laguna 4 - Puerto Nizuc (00175) | Q41: NO | R41: N/A | S41: =+J41 | U41: =+S41*21% | V41: =+S41*3% | W41: =+S41*0.3% | X41: =IF(A41="00-175",S41*0.06,0) | AA41: =+S41+T41+U41+W41+X41+V41+Y41 | AB41: 45987 | AC41: 2.3746108e+08 | AI41: =+AC41+AE41+AG41+AH41 | AJ41: =+AA41-AI41 | AK41: =IF(Q41="ANULADA","N/A",IF(ABS(AJ41)>10,"Pendiente",IF(MAX(AB41,AD41,AF41)=0,"Pendiente",MAX(0,MAX(AB41,AD41,AF41)-O41))))
A42: 00-175 | B42: NUEVA MARINAS DE HUDSON INVERSORA SA | C42: Laguna 4 - Puerto Nizuc | D42: Laguna 4 | E42: 5 | F42: Redet | G42: Redet. | H42: 45901 | J42: 21925985 | K42: 21925985 | L42: Validado | M42: FC A | N42: 2539 | O42: 45952 | P42: Certificado de Redeterminación Provisoria Nº 5 - Sep'25. - Laguna 4 - Puerto Nizuc (00175) | Q42: NO | R42: N/A | S42: =+J42 | U42: =+S42*21% | V42: =+S42*3% | W42: =+S42*0.3% | X42: =IF(A42="00-175",S42*0.06,0) | AA42: =+S42+T42+U42+W42+X42+V42+Y42 | AB42: 45987 | AC42: 28384065 | AD42: 45973 | AE42: 185492.71 | AI42: =+AC42+AE42+AG42+AH42 | AJ42: =+AA42-AI42 | AK42: =IF(Q42="ANULADA","N/A",IF(ABS(AJ42)>10,"Pendiente",IF(MAX(AB42,AD42,AF42)=0,"Pendiente",MAX(0,MAX(AB42,AD42,AF42)-O42))))
A43: 00-175 | B43: NUEVA MARINAS DE HUDSON INVERSORA SA | C43: Laguna 4 - Puerto Nizuc | D43: Polder | E43: 5 | F43: Basico polder | G43: Básico | H43: 45901 | J43: 48541827 | K43: 48541827 | L43: Validado | M43: FC A | N43: 2540 | O43: 45953 | P43: Certificado Nº 1 - Sep'25. Camino del Polder. - Laguna 4 - Puerto Nizuc (00175) | Q43: NO | R43: N/A | S43: =+J43 | U43: =+S43*21% | V43: =+S43*3% | W43: =+S43*0.3% | X43: =IF(A43="00-175",S43*0.06,0) | AA43: =+S43+T43+U43+W43+X43+V43+Y43 | AB43: 45988 | AC43: 63250000 | AI43: =+AC43+AE43+AG43+AH43 | AJ43: =+AA43-AI43 | AK43: =IF(Q43="ANULADA","N/A",IF(ABS(AJ43)>10,"Pendiente",IF(MAX(AB43,AD43,AF43)=0,"Pendiente",MAX(0,MAX(AB43,AD43,AF43)-O43))))
A44: 00-175 | B44: NUEVA MARINAS DE HUDSON INVERSORA SA | C44: Laguna 4 - Puerto Nizuc | D44: Polder | E44: 5 | F44: Redet polder | G44: Redet. | H44: 45901 | J44: 3262010.7 | K44: 3262010.7 | L44: Validado | M44: FC A | N44: 2541 | O44: 45953 | P44: Certificado de Redeterminación Provisoria Nº 1 - Sep'25. - Laguna 4 - Puerto Nizuc (00175) | Q44: NO | R44: N/A | S44: =+J44 | U44: =+S44*21% | V44: =+S44*3% | W44: =+S44*0.3% | X44: =IF(A44="00-175",S44*0.06,0) | AA44: =+S44+T44+U44+W44+X44+V44+Y44 | AB44: 45988 | AC44: 4250400 | AI44: =+AC44+AE44+AG44+AH44 | AJ44: =+AA44-AI44 | AK44: =IF(Q44="ANULADA","N/A",IF(ABS(AJ44)>10,"Pendiente",IF(MAX(AB44,AD44,AF44)=0,"Pendiente",MAX(0,MAX(AB44,AD44,AF44)-O44))))
A45: 00-175 | B45: NUEVA MARINAS DE HUDSON INVERSORA SA | C45: Laguna 4 - Puerto Nizuc | D45: Laguna 4 | E45: 6 | F45: Basico | G45: Básico | H45: 45931 | J45: 2.4750722e+08 | K45: 2.4750722e+08 | L45: Validado | M45: FC A | N45: 2551 | O45: 45988 | P45: Certificado Basico Nº 6 - oct'25 - Laguna 4 - Puerto Nizuc (00175) | Q45: NO | R45: N/A | S45: =+J45 | U45: =+S45*21% | W45: =+S45*0.3% | X45: =IF(A45="00-175",S45*0.06,0) | AA45: =+S45+T45+U45+W45+X45+V45+Y45 | AB45: 46003 | AC45: 3.1507668e+08 | AI45: =+AC45+AE45+AG45+AH45 | AJ45: =+AA45-AI45 | AK45: =IF(Q45="ANULADA","N/A",IF(ABS(AJ45)>10,"Pendiente",IF(MAX(AB45,AD45,AF45)=0,"Pendiente",MAX(0,MAX(AB45,AD45,AF45)-O45))))
A46: 00-175 | B46: NUEVA MARINAS DE HUDSON INVERSORA SA | C46: Laguna 4 - Puerto Nizuc | D46: Laguna 4 | E46: 6 | F46: Redet | G46: Redet. | H46: 45931 | J46: 44730629 | K46: 44730629 | L46: Validado | M46: FC A | N46: 2552 | O46: 45988 | P46: Certificado de Redeterminación de Precios Provisoria Nº 6 - oct'25 - Laguna 4 - Puerto Nizuc (00175) | Q46: NO | R46: N/A | S46: =+J46 | U46: =+S46*21% | W46: =+S46*0.3% | X46: =IF(A46="00-175",S46*0.06,0) | AA46: =+S46+T46+U46+W46+X46+V46+Y46 | AB46: 46003 | AC46: 56942090 | AI46: =+AC46+AE46+AG46+AH46 | AJ46: =+AA46-AI46 | AK46: =IF(Q46="ANULADA","N/A",IF(ABS(AJ46)>10,"Pendiente",IF(MAX(AB46,AD46,AF46)=0,"Pendiente",MAX(0,MAX(AB46,AD46,AF46)-O46))))
A47: 00-175 | B47: NUEVA MARINAS DE HUDSON INVERSORA SA | C47: Laguna 4 - Puerto Nizuc | D47: Laguna 4 | E47: 7 | F47: Basico | G47: Básico | H47: 45962 | J47: 1.6706404e+08 | K47: 1.6706404e+08 | L47: Validado | M47: FC A | N47: 2556 | O47: 46028 | P47: Certificado Nº 7 - Nov'25 - Laguna 4 - Puerto Nizuc (00175) | Q47: NO | R47: N/A | S47: =+J47 | U47: =+S47*21% | V47: =+S47*3% | W47: =+S47*0.3% | X47: =IF(A47="00-175",S47*0.06,0) | AA47: =+S47+T47+U47+W47+X47+V47+Y47 | AB47: 46078 | AC47: 2.1194141e+08 | AD47: 46121 | AE47: 5743032.7 | AI47: =+AC47+AE47+AG47+AH47 | AJ47: =+AA47-AI47 | AK47: =IF(Q47="ANULADA","N/A",IF(ABS(AJ47)>10,"Pendiente",IF(MAX(AB47,AD47,AF47)=0,"Pendiente",MAX(0,MAX(AB47,AD47,AF47)-O47))))
A48: 00-175 | B48: NUEVA MARINAS DE HUDSON INVERSORA SA | C48: Laguna 4 - Puerto Nizuc | D48: Laguna 4 | E48: 7 | F48: Redet | G48: Redet. | H48: 45962 | J48: 37711659 | K48: 37711659 | L48: Validado | M48: FC A | N48: 2557 | O48: 46028 | P48: Certificado de Redeterminación de Precios Provisoria Nº 7 - Nov'25 - Laguna 4 - Puerto Nizuc (00175) | Q48: NO | R48: N/A | S48: =+J48 | U48: =+S48*21% | V48: =+S48*3% | W48: =+S48*0.3% | X48: =IF(A48="00-175",S48*0.06,0) | AA48: =+S48+T48+U48+W48+X48+V48+Y48 | AB48: 46078 | AC48: 49138292 | AI48: =+AC48+AE48+AG48+AH48 | AJ48: =+AA48-AI48 | AK48: =IF(Q48="ANULADA","N/A",IF(ABS(AJ48)>10,"Pendiente",IF(MAX(AB48,AD48,AF48)=0,"Pendiente",MAX(0,MAX(AB48,AD48,AF48)-O48))))
A49: 00-175 | B49: NUEVA MARINAS DE HUDSON INVERSORA SA | C49: Laguna 4 - Puerto Nizuc | D49: Laguna 4 | E49: 8 | F49: Basico | G49: Básico | H49: 45992 | J49: 95486782 | K49: 95486782 | L49: Validado | M49: FC A | N49: 2569 | O49: 46053 | P49: Certificado Nº 8 - Dic'25.. - Laguna 4 - Puerto Nizuc (00175) | Q49: NO | R49: N/A | S49: =+J49 | U49: =+S49*21% | V49: =+S49*3% | W49: =+S49*0.3% | X49: =IF(A49="00-175",S49*0.06,0) | AA49: =+S49+T49+U49+W49+X49+V49+Y49 | AB49: 46078 | AC49: 1.2441928e+08 | AI49: =+AC49+AE49+AG49+AH49 | AJ49: =+AA49-AI49 | AK49: =IF(Q49="ANULADA","N/A",IF(ABS(AJ49)>10,"Pendiente",IF(MAX(AB49,AD49,AF49)=0,"Pendiente",MAX(0,MAX(AB49,AD49,AF49)-O49))))
A50: 00-175 | B50: NUEVA MARINAS DE HUDSON INVERSORA SA | C50: Laguna 4 - Puerto Nizuc | D50: Laguna 4 | E50: 8 | F50: Redet | G50: Redet. | H50: 45992 | J50: 22839845 | K50: 22839845 | L50: Validado | M50: FC A | N50: 2570 | O50: 46053 | P50: Certificado de Redeterminación Provisoria Nº 8 - Dic'25. - Laguna 4 - Puerto Nizuc (00175) | Q50: NO | R50: N/A | S50: =+J50 | U50: =+S50*21% | V50: =+S50*3% | W50: =+S50*0.3% | X50: =IF(A50="00-175",S50*0.06,0) | AA50: =+S50+T50+U50+W50+X50+V50+Y50 | AB50: 46078 | AC50: 29760318 | AI50: =+AC50+AE50+AG50+AH50 | AJ50: =+AA50-AI50 | AK50: =IF(Q50="ANULADA","N/A",IF(ABS(AJ50)>10,"Pendiente",IF(MAX(AB50,AD50,AF50)=0,"Pendiente",MAX(0,MAX(AB50,AD50,AF50)-O50))))
A51: 00-175 | B51: NUEVA MARINAS DE HUDSON INVERSORA SA | C51: Laguna 4 - Puerto Nizuc | D51: Laguna 4 | E51: 9 | F51: Basico | G51: Básico | H51: 46023 | J51: 1.0991241e+08 | K51: 1.0991241e+08 | L51: Validado | M51: FC A | N51: 2582 | O51: 46076 | P51: Certificado Nº 9 - Ene'26.. - Laguna 4 - Puerto Nizuc (00175) | Q51: NO | R51: N/A | S51: =+J51 | U51: =+S51*21% | V51: =+S51*3% | W51: =+S51*0.3% | X51: =IF(A51="00-175",S51*0.06,0) | AA51: =+S51+T51+U51+W51+X51+V51+Y51 | AB51: 46121 | AC51: 1.4321587e+08 | AI51: =+AC51+AE51+AG51+AH51 | AJ51: =+AA51-AI51 | AK51: =IF(Q51="ANULADA","N/A",IF(ABS(AJ51)>10,"Pendiente",IF(MAX(AB51,AD51,AF51)=0,"Pendiente",MAX(0,MAX(AB51,AD51,AF51)-O51))))
A52: 00-175 | B52: NUEVA MARINAS DE HUDSON INVERSORA SA | C52: Laguna 4 - Puerto Nizuc | D52: Laguna 4 | E52: 9 | F52: Redet | G52: Redet. | H52: 46023 | J52: 24692104 | K52: 24692104 | L52: Validado | M52: FC A | N52: 2583 | O52: 46076 | P52: Certificado de Redeterminación Provisoria Nº 9 - Ene'26. - Laguna 4 - Puerto Nizuc (00175) | Q52: NO | R52: N/A | S52: =+J52 | U52: =+S52*21% | V52: =+S52*3% | W52: =+S52*0.3% | X52: =IF(A52="00-175",S52*0.06,0) | AA52: =+S52+T52+U52+W52+X52+V52+Y52 | AB52: 46121 | AC52: 32173811 | AD52: 46121 | AI52: =+AC52+AE52+AG52+AH52 | AJ52: =+AA52-AI52 | AK52: =IF(Q52="ANULADA","N/A",IF(ABS(AJ52)>10,"Pendiente",IF(MAX(AB52,AD52,AF52)=0,"Pendiente",MAX(0,MAX(AB52,AD52,AF52)-O52))))
A53: 00-175 | B53: NUEVA MARINAS DE HUDSON INVERSORA SA | C53: Laguna 4 - Puerto Nizuc | D53: Alquiler de equipos | E53: 9 | F53: Alquiler equipo | G53: Básico | H53: 46023 | J53: 13950000 | K53: 13950000 | L53: Validado | M53: FC A | N53: 2587 | O53: 46076 | P53: Certificado Nº 1 - Ene'26.. - Laguna 4 - Puerto Nizuc (00175) | Q53: NO | R53: N/A | S53: =+J53 | U53: =+S53*21% | V53: =+S53*3% | W53: =+S53*0.3% | X53: =IF(A53="00-175",S53*0.06,0) | AA53: =+S53+T53+U53+W53+X53+V53+Y53 | AB53: 46121 | AC53: 18176278 | AD53: 46141 | AE53: 571.89 | AI53: =+AC53+AE53+AG53+AH53 | AJ53: =+AA53-AI53 | AK53: =IF(Q53="ANULADA","N/A",IF(ABS(AJ53)>10,"Pendiente",IF(MAX(AB53,AD53,AF53)=0,"Pendiente",MAX(0,MAX(AB53,AD53,AF53)-O53))))
A54: 00-175 | B54: NUEVA MARINAS DE HUDSON INVERSORA SA | C54: Laguna 4 - Puerto Nizuc | D54: Laguna 4 | E54: 10 | F54: Basico | G54: Básico | H54: 46054 | J54: 1938001.1 | K54: 1938001.1 | L54: Validado | M54: FC A | N54: 2600 | O54: 46132 | P54: Certificado Nº 10 - Feb'26. | Q54: NO | R54: N/A | S54: =+J54 | U54: =+S54*21% | V54: =+S54*3% | W54: =+S54*0.3% | X54: =IF(A54="00-175",S54*0.06,0) | AA54: =+S54+T54+U54+W54+X54+V54+Y54 | AB54: 46141 | AC54: 2525215.5 | AI54: =+AC54+AE54+AG54+AH54 | AJ54: =+AA54-AI54 | AK54: =IF(Q54="ANULADA","N/A",IF(ABS(AJ54)>10,"Pendiente",IF(MAX(AB54,AD54,AF54)=0,"Pendiente",MAX(0,MAX(AB54,AD54,AF54)-O54))))
A55: 00-175 | B55: NUEVA MARINAS DE HUDSON INVERSORA SA | C55: Laguna 4 - Puerto Nizuc | D55: Laguna 4 | E55: 10 | F55: Redet | G55: Redet. | H55: 46054 | J55: 3529738.5 | K55: 3529738.5 | L55: Validado | M55: FC A | N55: 2601 | O55: 46132 | P55: Redeterminación Provisoria Nº 10 - Feb'26. y Redeterminación Definitiva Nº 9 - Ene'26. | Q55: NO | R55: N/A | S55: =+J55 | U55: =+S55*21% | V55: =+S55*3% | W55: =+S55*0.3% | X55: =IF(A55="00-175",S55*0.06,0) | AA55: =+S55+T55+U55+W55+X55+V55+Y55 | AB55: 46141 | AC55: 4599249.3 | AI55: =+AC55+AE55+AG55+AH55 | AJ55: =+AA55-AI55 | AK55: =IF(Q55="ANULADA","N/A",IF(ABS(AJ55)>10,"Pendiente",IF(MAX(AB55,AD55,AF55)=0,"Pendiente",MAX(0,MAX(AB55,AD55,AF55)-O55))))
A56: 00-175 | B56: NUEVA MARINAS DE HUDSON INVERSORA SA | C56: Laguna 4 - Puerto Nizuc | D56: Laguna 4 | E56: 11 | F56: Basico | G56: Básico | H56: 46082 | J56: 33135158 | K56: 33135158 | L56: Validado | M56: FC A | N56: 2602 | O56: 46132 | P56: Certificado Nº 11 - Mar'26.. | Q56: NO | R56: N/A | S56: =+J56 | U56: =+S56*21% | V56: =+S56*3% | W56: =+S56*0.3% | X56: =IF(A56="00-175",S56*0.06,0) | AA56: =+S56+T56+U56+W56+X56+V56+Y56 | AB56: 46141 | AC56: 43175110 | AI56: =+AC56+AE56+AG56+AH56 | AJ56: =+AA56-AI56 | AK56: =IF(Q56="ANULADA","N/A",IF(ABS(AJ56)>10,"Pendiente",IF(MAX(AB56,AD56,AF56)=0,"Pendiente",MAX(0,MAX(AB56,AD56,AF56)-O56))))
A57: 00-175 | B57: NUEVA MARINAS DE HUDSON INVERSORA SA | C57: Laguna 4 - Puerto Nizuc | D57: Laguna 4 | E57: 11 | F57: Redet | G57: Redet. | H57: 46082 | J57: 8473458.6 | K57: 8473458.6 | L57: Validado | M57: FC A | N57: 2603 | O57: 46132 | P57: Redeterminación Provisoria Nº 11 - Mar'26 y Redeterminación Definitiva Nº 10 - Feb'26. | Q57: NO | R57: N/A | S57: =+J57 | U57: =+S57*21% | V57: =+S57*3% | W57: =+S57*0.3% | X57: =IF(A57="00-175",S57*0.06,0) | AA57: =+S57+T57+U57+W57+X57+V57+Y57 | AB57: 46141 | AC57: 11040671 | AI57: =+AC57+AE57+AG57+AH57 | AJ57: =+AA57-AI57 | AK57: =IF(Q57="ANULADA","N/A",IF(ABS(AJ57)>10,"Pendiente",IF(MAX(AB57,AD57,AF57)=0,"Pendiente",MAX(0,MAX(AB57,AD57,AF57)-O57))))
A58: 00-175 | B58: NUEVA MARINAS DE HUDSON INVERSORA SA | C58: Laguna 4 - Puerto Nizuc | D58: Laguna 4 | E58: 12 | F58: Basico | G58: Basico | H58: 46113 | J58: 22282672 | K58: 22282672 | L58: Validado | M58: FC A | N58: 2626 | O58: 46178 | P58: Certificado Nº 12 - Abr'26. | Q58: NO | R58: N/A | S58: =+K58 | U58: =+S58*21% | V58: =+S58*3% | W58: =+S58*0.3% | X58: =IF(A58="00-175",S58*0.06,0) | AA58: =+S58+T58+U58+W58+X58+V58+Y58 | AI58: =+AC58+AE58+AG58+AH58 | AJ58: =+AA58-AI58 | AK58: =IF(Q58="ANULADA","N/A",IF(ABS(AJ58)>10,"Pendiente",IF(MAX(AB58,AD58,AF58)=0,"Pendiente",MAX(0,MAX(AB58,AD58,AF58)-O58))))
A59: 00-175 | B59: NUEVA MARINAS DE HUDSON INVERSORA SA | C59: Laguna 4 - Puerto Nizuc | D59: Laguna 4 | E59: 12 | F59: Redet | G59: Redet. | H59: 46113 | J59: 6813690.4 | K59: 6813690.4 | L59: Validado | M59: FC A | N59: 2627 | O59: 46178 | P59: Certificado de Redeterminación Provisoria Nº 12 - Abr'26 + Certificado de Redeterminación Definitiva Nº 11 - Mar'26 | Q59: NO | R59: N/A | S59: =+K59 | U59: =+S59*21% | V59: =+S59*3% | W59: =+S59*0.3% | X59: =IF(A59="00-175",S59*0.06,0) | AA59: =+S59+T59+U59+W59+X59+V59+Y59 | AI59: =+AC59+AE59+AG59+AH59 | AJ59: =+AA59-AI59 | AK59: =IF(Q59="ANULADA","N/A",IF(ABS(AJ59)>10,"Pendiente",IF(MAX(AB59,AD59,AF59)=0,"Pendiente",MAX(0,MAX(AB59,AD59,AF59)-O59))))
A60: 00-176a | B60: FIDEICOMISO MARINAS DEL PLATA | C60: Asfalto Etapa 2 A - Puerto Nizuc | D60: Bacheo de emergencia | E60: 1 | F60: Basico Bacheo | G60: Básico | H60: 45870 | J60: 56684269 | K60: 56684269 | L60: Validado | M60: FC A | N60: 2515 | O60: 45925 | P60: Certificado Básico Nº1 Bacheo de Emergencia - Ago'25. - Asfalto Etapa 2 A - Puerto Nizuc (00176) | Q60: NO | R60: N/A | S60: =+J60 | U60: =+S60*21% | V60: =+S60*3% | W60: =+S60*2.5% | X60: =IF(A60="00-175",S60*0.06,0) | AA60: =+S60+T60+U60+W60+X60+V60+Y60 | AB60: 45939 | AC60: 7258769.2 | AD60: 45958 | AE60: 64441927 | AF60: 45988 | AG60: 4904.43 | AI60: =+AC60+AE60+AG60+AH60 | AJ60: =+AA60-AI60 | AK60: =IF(Q60="ANULADA","N/A",IF(ABS(AJ60)>10,"Pendiente",IF(MAX(AB60,AD60,AF60)=0,"Pendiente",MAX(0,MAX(AB60,AD60,AF60)-O60))))
A61: 00-176a | B61: FIDEICOMISO MARINAS DEL PLATA | C61: Asfalto Etapa 2 A - Puerto Nizuc | D61: Bacheo de emergencia | E61: 2 | F61: Basico Bacheo | G61: Básico | H61: 45901 | J61: 8659893.5 | K61: 8659893.5 | L61: Validado | M61: FC A | N61: 2542 | O61: 45953 | P61: Certificado Básico Nº 2 Bacheo de Emergencia - Sep'25. - Asfalto Etapa 2 A - Puerto Nizuc (00176) | Q61: NO | R61: N/A | S61: =+J61 | U61: =+S61*21% | V61: =+S61*3% | W61: =+S61*2.5% | X61: =IF(A61="00-175",S61*0.06,0) | AA61: =+S61+T61+U61+W61+X61+V61+Y61 | AB61: 45988 | AC61: 10954765 | AI61: =+AC61+AE61+AG61+AH61 | AJ61: =+AA61-AI61 | AK61: =IF(Q61="ANULADA","N/A",IF(ABS(AJ61)>10,"Pendiente",IF(MAX(AB61,AD61,AF61)=0,"Pendiente",MAX(0,MAX(AB61,AD61,AF61)-O61))))
A62: 00-176a | B62: FIDEICOMISO MARINAS DEL PLATA | C62: Asfalto Etapa 2 A - Puerto Nizuc | D62: Bacheo de emergencia | E62: 2 | F62: Redet Bacheo | G62: Redet. | H62: 45901 | J62: 954024.77 | K62: 954024.77 | L62: Validado | M62: FC A | N62: 2543 | O62: 45953 | P62: Certificado de Redeterminación Provisorio Nº 2 - Sep'25. - Asfalto Etapa 2 A - Puerto Nizuc (00176) | Q62: NO | R62: N/A | S62: =+J62 | U62: =+S62*21% | V62: =+S62*3% | W62: =+S62*2.5% | X62: =IF(A62="00-175",S62*0.06,0) | AA62: =+S62+T62+U62+W62+X62+V62+Y62 | AB62: 45988 | AC62: 1206841.3 | AI62: =+AC62+AE62+AG62+AH62 | AJ62: =+AA62-AI62 | AK62: =IF(Q62="ANULADA","N/A",IF(ABS(AJ62)>10,"Pendiente",IF(MAX(AB62,AD62,AF62)=0,"Pendiente",MAX(0,MAX(AB62,AD62,AF62)-O62))))
A63: 00-176b | B63: FIDEICOMISO MARINAS DEL PLATA | C63: Asfalto Etapa 2 A - Puerto Nizuc | D63: Obras sector 2 A | E63: 1 | F63: Basico Obras 2a | G63: Básico | H63: 45901 | J63: 130749094 | K63: 130749094 | L63: Validado | M63: FC A | N63: 2544 | O63: 45954 | P63: Certificado Básico Nº 1 - Sep'25. (Corresponde a U$D 93.392,21.- Tipo de Cambio 30/09/2025 = 1.400 $/U$D). - Asfalto Etapa 2 A - Puerto Nizuc (00176) | Q63: NO | R63: N/A | S63: =+J63 | U63: =+S63*21% | V63: =+S63*3% | W63: =+S63*2.5% | X63: =IF(A63="00-175",S63*0.06,0) | AA63: =+S63+T63+U63+W63+X63+V63+Y63 | AB63: 45988 | AC63: 1.3675881e+08 | AD63: 46064 | AE63: 28638799 | AI63: =+AC63+AE63+AG63+AH63 | AJ63: =+AA63-AI63 | AK63: =IF(Q63="ANULADA","N/A",IF(ABS(AJ63)>10,"Pendiente",IF(MAX(AB63,AD63,AF63)=0,"Pendiente",MAX(0,MAX(AB63,AD63,AF63)-O63))))
A64: 00-176b | B64: FIDEICOMISO MARINAS DEL PLATA | C64: Asfalto Etapa 2 A - Puerto Nizuc | D64: Obras sector 2 A | E64: 2 | F64: Basico Obras 2a | G64: Básico | H64: 45931 | J64: 3.997598e+08 | K64: 3.997598e+08 | L64: Validado | M64: FC A | N64: 2562 | O64: 46031 | P64: Certificado Básico Nº 2 - Oct'25. (Corresponde a U$D 271.023,59.- Tipo de Cambio 31/10/2025 = 1.475,00.- $/U$D) - Asfalt | Q64: NO | R64: N/A | S64: =+J64 | U64: =+S64*21% | V64: =+S64*3% | W64: =+S64*2.5% | X64: =IF(A64="00-175",S64*0.06,0) | AA64: =+S64+T64+U64+W64+X64+V64+Y64 | AB64: 46057 | AC64: 5.0569614e+08 | AI64: =+AC64+AE64+AG64+AH64 | AJ64: =+AA64-AI64 | AK64: =IF(Q64="ANULADA","N/A",IF(ABS(AJ64)>10,"Pendiente",IF(MAX(AB64,AD64,AF64)=0,"Pendiente",MAX(0,MAX(AB64,AD64,AF64)-O64))))
A65: 00-176b | B65: FIDEICOMISO MARINAS DEL PLATA | C65: Asfalto Etapa 2 A - Puerto Nizuc | D65: SAPECO 2A | E65: 2 | F65: Redet Obras 2a | G65: Redet. | H65: 45931 | J65: 47382371 | K65: 47382371 | L65: Validado | M65: FC A | N65: 2563 | O65: 46031 | P65: Certificado Básico Nº 1 - Oct'25. Dirección de Obra a subcontrato SAPECO. - Asfalto Etapa 2 A - Puerto Nizuc (00176) | Q65: NO | R65: N/A | S65: =+J65 | U65: =+S65*21% | V65: =+S65*3% | W65: =+S65*2.5% | X65: =IF(A65="00-175",S65*0.06,0) | AA65: =+S65+T65+U65+W65+X65+V65+Y65 | AB65: 46036 | AC65: 383.62 | AD65: 46057 | AE65: 59938315 | AI65: =+AC65+AE65+AG65+AH65 | AJ65: =+AA65-AI65 | AK65: =IF(Q65="ANULADA","N/A",IF(ABS(AJ65)>10,"Pendiente",IF(MAX(AB65,AD65,AF65)=0,"Pendiente",MAX(0,MAX(AB65,AD65,AF65)-O65))))
A66: 00-176b | B66: FIDEICOMISO MARINAS DEL PLATA | C66: Asfalto Etapa 2 A - Puerto Nizuc | D66: Obras sector 2 A | E66: 3 | F66: Basico Obras 2a | G66: Básico | H66: 45962 | J66: 3.815259e+08 | K66: 3.815259e+08 | L66: Validado | M66: FC A | N66: 2564 | O66: 46031 | P66: Certificado Básico Nº 3 - Nov'25. (Corresponde a U$D 258.661,63.- Tipo de Cambio 28/11/2025 = 1.475,00.- $/U$D) - Asfalt | Q66: NO | R66: N/A | S66: =+J66 | U66: =+S66*21% | V66: =+S66*3% | W66: =+S66*2.5% | X66: =IF(A66="00-175",S66*0.06,0) | AA66: =+S66+T66+U66+W66+X66+V66+Y66 | AB66: 46036 | AC66: 403560.31 | AD66: 46079 | AE66: 7568028.2 | AF66: 46064 | AG66: 4.7465868e+08 | AI66: =+AC66+AE66+AG66+AH66 | AJ66: =+AA66-AI66 | AK66: =IF(Q66="ANULADA","N/A",IF(ABS(AJ66)>10,"Pendiente",IF(MAX(AB66,AD66,AF66)=0,"Pendiente",MAX(0,MAX(AB66,AD66,AF66)-O66))))
A67: 00-176b | B67: FIDEICOMISO MARINAS DEL PLATA | C67: Asfalto Etapa 2 A - Puerto Nizuc | D67: SAPECO 2A | E67: 3 | F67: Redet Obras 2a | G67: Redet. | H67: 45962 | J67: 16337413 | K67: 16337413 | L67: Validado | M67: FC A | N67: 2565 | O67: 46031 | P67: Certificado Básico Nº 2 - Nov'25. Dirección de Obra a subcontrato SAPECO. - Asfalto Etapa 2 A - Puerto Nizuc (00176) | Q67: NO | R67: N/A | S67: =+J67 | U67: =+S67*21% | V67: =+S67*3% | W67: =+S67*2.5% | X67: =IF(A67="00-175",S67*0.06,0) | AA67: =+S67+T67+U67+W67+X67+V67+Y67 | AB67: 46036 | AC67: 20666828 | AI67: =+AC67+AE67+AG67+AH67 | AJ67: =+AA67-AI67 | AK67: =IF(Q67="ANULADA","N/A",IF(ABS(AJ67)>10,"Pendiente",IF(MAX(AB67,AD67,AF67)=0,"Pendiente",MAX(0,MAX(AB67,AD67,AF67)-O67))))
A68: 00-176b | B68: FIDEICOMISO MARINAS DEL PLATA | C68: Asfalto Etapa 2 A - Puerto Nizuc | D68: Obras sector 2 A | E68: 4 | F68: Basico Obras 2a | G68: Básico | H68: 45992 | J68: 1.7632988e+08 | K68: 1.7632988e+08 | L68: Validado | M68: FC A | N68: 2567 | O68: 46053 | P68: Certificado Básico Nº 4 - Dic'25. (Corresponde a U$D 119.141,81.- Tipo de Cambio 31/12/2025 = 1.480,00.- $/U$D). - Asfal | Q68: NO | R68: N/A | S68: =+J68 | U68: =+S68*21% | V68: =+S68*3% | W68: =+S68*2.5% | X68: =IF(A68="00-175",S68*0.06,0) | AA68: =+S68+T68+U68+W68+X68+V68+Y68 | AB68: 46079 | AC68: 2.230573e+08 | AI68: =+AC68+AE68+AG68+AH68 | AJ68: =+AA68-AI68 | AK68: =IF(Q68="ANULADA","N/A",IF(ABS(AJ68)>10,"Pendiente",IF(MAX(AB68,AD68,AF68)=0,"Pendiente",MAX(0,MAX(AB68,AD68,AF68)-O68))))
A69: 00-176b | B69: FIDEICOMISO MARINAS DEL PLATA | C69: Asfalto Etapa 2 A - Puerto Nizuc | D69: SAPECO 2A | E69: 4 | F69: Redet Obras 2a | G69: Redet. | H69: 45992 | J69: 7099658.8 | K69: 7099658.8 | L69: Validado | M69: FC A | N69: 2568 | O69: 46053 | P69: Certificado Básico Nº 3 - Dic'25. Dirección de Obra a subcontrato SAPECO. - Asfalto Etapa 2 A - Puerto Nizuc (00176) | Q69: NO | R69: N/A | S69: =+J69 | U69: =+S69*21% | V69: =+S69*3% | W69: =+S69*2.5% | X69: =IF(A69="00-175",S69*0.06,0) | AA69: =+S69+T69+U69+W69+X69+V69+Y69 | AB69: 46072 | AC69: 8981068.4 | AI69: =+AC69+AE69+AG69+AH69 | AJ69: =+AA69-AI69 | AK69: =IF(Q69="ANULADA","N/A",IF(ABS(AJ69)>10,"Pendiente",IF(MAX(AB69,AD69,AF69)=0,"Pendiente",MAX(0,MAX(AB69,AD69,AF69)-O69))))
A70: 00-176b | B70: FIDEICOMISO MARINAS DEL PLATA | C70: Asfalto Etapa 2 A - Puerto Nizuc | D70: Obras sector 2 A | E70: 5 | F70: Basico Obras 2a | G70: Básico | H70: 46023 | J70: 1.313359e+08 | K70: 1.313359e+08 | L70: Validado | M70: FC A | N70: 2595 | O70: 46132 | P70: Certificado Básico Nº 5 - Ene'26. (Corresponde a U$D 89.649,08.- Tipo de Cambio 31/01/2026 = 1.465,00.- $/U$D) | Q70: NO | R70: N/A | S70: =+J70 | U70: =+S70*21% | V70: =+S70*3% | W70: =+S70*2.5% | X70: =IF(A70="00-175",S70*0.06,0) | AA70: =+S70+T70+U70+W70+X70+V70+Y70 | AB70: 46141 | AC70: 1.6613992e+08 | AI70: =+AC70+AE70+AG70+AH70 | AJ70: =+AA70-AI70 | AK70: =IF(Q70="ANULADA","N/A",IF(ABS(AJ70)>10,"Pendiente",IF(MAX(AB70,AD70,AF70)=0,"Pendiente",MAX(0,MAX(AB70,AD70,AF70)-O70))))
A71: 00-176b | B71: FIDEICOMISO MARINAS DEL PLATA | C71: Asfalto Etapa 2 A - Puerto Nizuc | D71: SAPECO 2A | E71: 5 | F71: Redet Obras 2a | G71: Redet. | H71: 46023 | J71: 5408883.7 | K71: 5408883.7 | L71: Validado | M71: FC A | N71: 2596 | O71: 46132 | P71: Certificado Básico Nº 4 - Ene'26. Dirección de Obra a subcontrato SAPECO.. | Q71: NO | R71: N/A | S71: =+J71 | U71: =+S71*21% | V71: =+S71*3% | W71: =+S71*2.5% | X71: =IF(A71="00-175",S71*0.06,0) | AA71: =+S71+T71+U71+W71+X71+V71+Y71 | AI71: =+AC71+AE71+AG71+AH71 | AJ71: =+AA71-AI71 | AK71: =IF(Q71="ANULADA","N/A",IF(ABS(AJ71)>10,"Pendiente",IF(MAX(AB71,AD71,AF71)=0,"Pendiente",MAX(0,MAX(AB71,AD71,AF71)-O71))))
A72: 00-176b | B72: FIDEICOMISO MARINAS DEL PLATA | C72: Asfalto Etapa 2 A - Puerto Nizuc | G72: Básico | H72: 46054 | J72: 0 | K72: 0 | M72: FC A | N72: 2597 | O72: 46132 | P72: Certificado Básico Nº 6 - Feb'26 (Corresponde a U$D 20.713,80.- Tipo de Cambio 27/02/2026 = 1.420,00.- $/U$D). | Q72: ANULADA | R72: 365 | S72: =+J72 | U72: =+S72*21% | V72: =+S72*3% | W72: =+S72*2.5% | X72: =IF(A72="00-175",S72*0.06,0) | AA72: =+S72+T72+U72+W72+X72+V72+Y72 | AI72: =+AC72+AE72+AG72+AH72 | AJ72: =+AA72-AI72 | AK72: =IF(Q72="ANULADA","N/A",IF(ABS(AJ72)>10,"Pendiente",IF(MAX(AB72,AD72,AF72)=0,"Pendiente",MAX(0,MAX(AB72,AD72,AF72)-O72))))
A73: 00-176b | B73: FIDEICOMISO MARINAS DEL PLATA | C73: Asfalto Etapa 2 A - Puerto Nizuc | D73: SAPECO 2A | E73: 6 | F73: Redet Obras 2a | G73: Redet. | H73: 46054 | J73: 20970962 | K73: 20970962 | L73: Validado | M73: FC A | N73: 2598 | O73: 46132 | P73: Certificado Básico Nº 5 - Feb'26. Dirección de Obra a subcontrato SAPECO.. | Q73: NO | R73: N/A | S73: =+J73 | U73: =+S73*21% | V73: =+S73*3% | W73: =+S73*2.5% | X73: =IF(A73="00-175",S73*0.06,0) | AA73: =+S73+T73+U73+W73+X73+V73+Y73 | AB73: 46141 | AC73: 26528267 | AI73: =+AC73+AE73+AG73+AH73 | AJ73: =+AA73-AI73 | AK73: =IF(Q73="ANULADA","N/A",IF(ABS(AJ73)>10,"Pendiente",IF(MAX(AB73,AD73,AF73)=0,"Pendiente",MAX(0,MAX(AB73,AD73,AF73)-O73))))
A74: 00-176b | B74: FIDEICOMISO MARINAS DEL PLATA | C74: Asfalto Etapa 2 A - Puerto Nizuc | D74: SAPECO 2A | E74: 7 | F74: Redet Obras 2a | G74: Básico | H74: 46082 | J74: 5187359.5 | K74: 5187359.5 | L74: Validado | M74: FC A | N74: 2599 | O74: 46132 | P74: Certificado Básico Nº 7 - Mar'26. Dirección de Obra a subcontrato SAPECO. | Q74: NO | R74: N/A | S74: =+J74 | U74: =+S74*21% | V74: =+S74*3% | W74: =+S74*2.5% | X74: =IF(A74="00-175",S74*0.06,0) | AA74: =+S74+T74+U74+W74+X74+V74+Y74 | AB74: 46141 | AC74: 6445309.7 | AI74: =+AC74+AE74+AG74+AH74 | AJ74: =+AA74-AI74 | AK74: =IF(Q74="ANULADA","N/A",IF(ABS(AJ74)>10,"Pendiente",IF(MAX(AB74,AD74,AF74)=0,"Pendiente",MAX(0,MAX(AB74,AD74,AF74)-O74))))
A75: 00-176b | B75: FIDEICOMISO MARINAS DEL PLATA | C75: Asfalto Etapa 2 A - Puerto Nizuc | D75: Obras sector 2 A | E75: 6 | F75: Basico Obras 2a | G75: Básico | H75: 46054 | J75: 29413596 | K75: 29413596 | L75: Validado | M75: FC A | N75: 2605 | O75: 46133 | P75: Certificado Básico Nº 6 - Feb'26 (Corresponde a U$D 20.713,80.- Tipo de Cambio 27/02/2026 = 1.420,00.- $/U$D). | Q75: NO | R75: N/A | S75: =+J75 | U75: =+S75*21% | V75: =+S75*3% | W75: =+S75*2.5% | X75: =IF(A75="00-175",S75*0.06,0) | AA75: =+S75+T75+U75+W75+X75+V75+Y75 | AB75: 46162 | AC75: 37208199 | AI75: =+AC75+AE75+AG75+AH75 | AJ75: =+AA75-AI75 | AK75: =IF(Q75="ANULADA","N/A",IF(ABS(AJ75)>10,"Pendiente",IF(MAX(AB75,AD75,AF75)=0,"Pendiente",MAX(0,MAX(AB75,AD75,AF75)-O75))))
A76: 00-176 | B76: FIDEICOMISO MARINAS DEL PLATA | C76: Asfalto Etapa 2 A - Puerto Nizuc | D76: PAVIMENTACIÓN 2A/ 2B/ L5 / L6/ L7/ BOULEVARD | E76: 1 | F76: Basico Obras 2a | G76: Básico | H76: 46082 | J76: 1.6949607e+08 | K76: 1.6949607e+08 | L76: Validado | M76: FC A | N76: 2611 | O76: 46142 | P76: Certificado Básico Nº 1 - Mar'26. | Q76: NO | R76: N/A | S76: =+J76 | U76: =+S76*21% | V76: =+S76*3% | W76: =+S76*2.5% | X76: =IF(A76="00-175",S76*0.06,0) | AA76: =+S76+T76+U76+W76+X76+V76+Y76 | AB76: 46162 | AC76: 2.1441253e+08 | AI76: =+AC76+AE76+AG76+AH76 | AJ76: =+AA76-AI76 | AK76: =IF(Q76="ANULADA","N/A",IF(ABS(AJ76)>10,"Pendiente",IF(MAX(AB76,AD76,AF76)=0,"Pendiente",MAX(0,MAX(AB76,AD76,AF76)-O76))))
A77: 00-176 | B77: FIDEICOMISO MARINAS DEL PLATA | C77: Asfalto Etapa 2 A - Puerto Nizuc | D77: PAVIMENTACIÓN 2A/ 2B/ L5 / L6/ L7/ BOULEVARD | E77: 1 | F77: Redet Obras 2a | G77: Básico | H77: 46082 | J77: 6106787.4 | K77: 6106787.4 | L77: Validado | M77: FC A | N77: 2612 | O77: 46142 | P77: Certificado de Redeterminación Provisorio Nº 1 - Mar'26 | Q77: NO | R77: N/A | S77: =+J77 | U77: =+S77*21% | V77: =+S77*3% | W77: =+S77*2.5% | X77: =IF(A77="00-175",S77*0.06,0) | AA77: =+S77+T77+U77+W77+X77+V77+Y77 | AB77: 46162 | AC77: 7724860.1 | AI77: =+AC77+AE77+AG77+AH77 | AJ77: =+AA77-AI77 | AK77: =IF(Q77="ANULADA","N/A",IF(ABS(AJ77)>10,"Pendiente",IF(MAX(AB77,AD77,AF77)=0,"Pendiente",MAX(0,MAX(AB77,AD77,AF77)-O77))))
A78: 00-176c | B78: FIDEICOMISO MARINAS DEL PLATA | C78: Asfalto Etapa 2 A - Puerto Nizuc | D78: Pavimentacion Basico | E78: 2 | F78: Basico Obras 2a | G78: Basico | H78: 46113 | J78: 4.2095298e+08 | K78: 4.2095298e+08 | L78: Validado | M78: FC A | N78: 2628 | O78: 46178 | Q78: NO | R78: N/A | S78: =+K78 | U78: =+S78*21% | V78: =+S78*3% | W78: =+S78*2.5% | X78: =IF(A78="00-175",S78*0.06,0) | AA78: =+S78+T78+U78+W78+X78+V78+Y78 | AI78: =+AC78+AE78+AG78+AH78 | AJ78: =+AA78-AI78 | AK78: =IF(Q78="ANULADA","N/A",IF(ABS(AJ78)>10,"Pendiente",IF(MAX(AB78,AD78,AF78)=0,"Pendiente",MAX(0,MAX(AB78,AD78,AF78)-O78))))
A79: 00-176c | B79: FIDEICOMISO MARINAS DEL PLATA | C79: Asfalto Etapa 2 A - Puerto Nizuc | D79: Pavimentacion Redet | E79: 2 | F79: Basico Obras 2a | G79: Redet. | H79: 46113 | J79: 25172720 | K79: =+J79 | L79: Validado | M79: FC A | N79: 2629 | O79: 46178 | P79: Redeterminación Provisorio Nº 2 - Abr'26 + Redeterminación Definitivo Nº 1 - Mar'26 | Q79: NO | R79: N/A | S79: =+K79 | U79: =+S79*21% | V79: =+S79*3% | W79: =+S79*2.5% | X79: =IF(A79="00-175",S79*0.06,0) | AA79: =+S79+T79+U79+W79+X79+V79+Y79 | AI79: =+AC79+AE79+AG79+AH79 | AJ79: =+AA79-AI79 | AK79: =IF(Q79="ANULADA","N/A",IF(ABS(AJ79)>10,"Pendiente",IF(MAX(AB79,AD79,AF79)=0,"Pendiente",MAX(0,MAX(AB79,AD79,AF79)-O79))))
A80: 00-176d | B80: FIDEICOMISO MARINAS DEL PLATA | C80: Asfalto Etapa 2 A - Puerto Nizuc | D80: Redet. REPARACION DE CORDONES Y BADENES ETAPA 2 | E80: 1 | F80: Redet Obras 2a | G80: Redet. | H80: 46082 | J80: 37258109 | K80: =+J80 | L80: En Espera | U80: =+S80*21% | V80: =+S80*3% | W80: =+S80*0.3% | X80: =IF(A80="00-175",S80*0.06,0) | AA80: =+S80+T80+U80+W80+X80+V80+Y80 | AI80: =+AC80+AE80+AG80+AH80 | AJ80: =+AA80-AI80 | AK80: =IF(Q80="ANULADA","N/A",IF(ABS(AJ80)>10,"Pendiente",IF(MAX(AB80,AD80,AF80)=0,"Pendiente",MAX(0,MAX(AB80,AD80,AF80)-O80))))
A81: 00-176d | B81: FIDEICOMISO MARINAS DEL PLATA | C81: Asfalto Etapa 2 A - Puerto Nizuc | D81: Basico REPARACION DE CORDONES Y BADENES ETAPA 2 | E81: 1 | F81: Basico Obras 2a | G81: Basico | H81: 46113 | J81: 1342357.4 | K81: =+J81 | L81: En Espera | U81: =+S81*21% | V81: =+S81*3% | W81: =+S81*0.3% | X81: =IF(A81="00-175",S81*0.06,0) | AA81: =+S81+T81+U81+W81+X81+V81+Y81 | AI81: =+AC81+AE81+AG81+AH81 | AJ81: =+AA81-AI81 | AK81: =IF(Q81="ANULADA","N/A",IF(ABS(AJ81)>10,"Pendiente",IF(MAX(AB81,AD81,AF81)=0,"Pendiente",MAX(0,MAX(AB81,AD81,AF81)-O81))))
A82: 00-177 | B82: EDIFICIOS PUERTO NIZUC FIDEICOMISO | C82: Edificios 7 y 8 - Puerto Nizuc | D82: Edificios 7 a 8 | E82: N/A | F82: Dev. Anticipo Financiero Certificado Dic'25 | G82: Dev. Anticipo | H82: 45992 | J82: -2.3284052e+09 | K82: -2.3284052e+09 | L82: Validado | M82: NC A | N82: 366 | O82: 46162 | P82: Devolución Anticipo Financiero Certificado Dic'25 | Q82: NO | R82: N/A | S82: -2.3284052e+09 | T82: -2.4448254e+08 | U82: 0 | V82: 0 | W82: -69852155 | X82: -81494181 | Y82: 0 | Z82: -34926078 | AA82: -2.7591601e+09 | AI82: 0 | AJ82: 0 | AK82: N/A
A83: 00-177 | B83: EDIFICIOS PUERTO NIZUC FIDEICOMISO | C83: Edificios 7 y 8 - Puerto Nizuc | D83: Edificios 7 a 8 | E83: N/A | F83: Dev. Anticipo Financiero Certificado Ene'26 | G83: Dev. Anticipo | H83: 46023 | J83: -1.5447276e+09 | K83: -1.5447276e+09 | L83: Validado | M83: NC A | N83: 367 | O83: 46162 | P83: Devolución Anticipo Financiero Certificado Ene'26 | Q83: NO | R83: N/A | S83: -1.5447276e+09 | T83: -1.621964e+08 | U83: 0 | V83: 0 | W83: -46341829 | X83: -54065467 | Y83: 0 | Z83: -23170914 | AA83: -1.8305022e+09 | AI83: 0 | AJ83: 0 | AK83: N/A
A84: 00-177 | B84: EDIFICIOS PUERTO NIZUC FIDEICOMISO | C84: Edificios 7 y 8 - Puerto Nizuc | D84: Edificios 7 a 8 | E84: N/A | F84: Dev. Anticipo Financiero Certificado Feb'26 | G84: Dev. Anticipo | H84: 46054 | J84: -8.5945514e+08 | K84: -8.5945514e+08 | L84: Validado | M84: NC A | N84: 368 | O84: 46162 | P84: Devolución Anticipo Financiero Certificado Feb'26 | Q84: NO | R84: N/A | S84: -8.5945514e+08 | T84: -90242790 | U84: 0 | V84: 0 | W84: -25783654 | X84: -30080930 | Y84: 0 | Z84: -12891827 | AA84: -1018454339 | AI84: 0 | AJ84: 0 | AK84: N/A
A85: 00-177 | B85: EDIFICIOS PUERTO NIZUC FIDEICOMISO | C85: Edificios 7 y 8 - Puerto Nizuc | D85: Edificios 7 a 8 | E85: 0 | G85: Anticipo | H85: Anticipo | M85: FC A | N85: 2545 | O85: 45964 | P85: Anticipo de Obra 20 %. - Edificios 5 al 8 - Puerto Nizuc (00177) | Q85: ANULADA | R85: 362 | S85: =+J85 | U85: =+S85*21% | V85: =+S85*3% | W85: =+S85*0.3% | X85: =IF(A85="00-175",S85*0.06,0) | AA85: =+S85+T85+U85+W85+X85+V85+Y85 | AI85: =+AC85+AE85+AG85+AH85 | AJ85: =+AA85-AI85 | AK85: =IF(Q85="ANULADA","N/A",IF(ABS(AJ85)>10,"Pendiente",IF(MAX(AB85,AD85,AF85)=0,"Pendiente",MAX(0,MAX(AB85,AD85,AF85)-O85))))
A86: 00-177 | B86: EDIFICIOS PUERTO NIZUC FIDEICOMISO | C86: Edificios 7 y 8 - Puerto Nizuc | D86: Edificios 7 a 8 | G86: Anticipo | H86: Anticipo | J86: 0 | K86: 4.8370062e+09 | L86: Validado | M86: FC A | N86: 2546 | O86: 45964 | P86: Anticipo de Obra. - Edificios 5 al 8 - Puerto Nizuc (00177) | Q86: NO | R86: N/A | S86: 4.8370062e+09 | T86: 5.0788565e+08 | U86: =+S86*21% | V86: =+S86*3% | W86: 1.4511019e+08 | X86: 1.6929522e+08 | AA86: 5.6592972e+09 | AB86: 46007 | AC86: 8.2229105e+08 | AD86: 46022 | AE86: 4.8370062e+09 | AI86: =+AC86+AE86+AG86+AH86+101000000 | AJ86: =+AA86-AI86 | AK86: 0
A87: 00-177 | B87: EDIFICIOS PUERTO NIZUC FIDEICOMISO | C87: Edificios 7 y 8 - Puerto Nizuc | D87: Edificios 7 a 8 | G87: Anticipo | H87: Anticipo | M87: FC A | N87: 2579 | O87: 46053 | P87: Anticipo de Obra. - Edificios 5 al 8 - Puerto Nizuc (00177) | Q87: ANULADA | R87: 363 | S87: =+J87 | U87: =+S87*21% | V87: =+S87*3% | W87: =+S87*0.3% | X87: =IF(A87="00-175",S87*0.06,0) | AA87: =+S87+T87+U87+W87+X87+V87+Y87 | AI87: =+AC87+AE87+AG87+AH87 | AJ87: =+AA87-AI87 | AK87: =IF(Q87="ANULADA","N/A",IF(ABS(AJ87)>10,"Pendiente",IF(MAX(AB87,AD87,AF87)=0,"Pendiente",MAX(0,MAX(AB87,AD87,AF87)-O87))))
A88: 00-177 | B88: EDIFICIOS PUERTO NIZUC FIDEICOMISO | C88: Edificios 7 y 8 - Puerto Nizuc | D88: Edificios 7 a 8 | E88: 1 | F88: Básico Nº 1 Cap 1 Dic'25 + CyC Nº 1 Cap 2-31 Oct/Nov/Dic'25 | G88: Básico | H88: 45992 | I88: 2.2873158e+09 | J88: 2.2873158e+09 | K88: 0 | L88: Validado | M88: FC A | N88: 2614 | O88: 46162 | P88: Certificado Básico Nº 1 - Cap 1 - Dic'25 / Costes y Costas Nº 1 - Cap 2-31 - Oct, Nov, Dic'25 | Q88: NO | R88: N/A | S88: 2.2873158e+09 | T88: 2.4016816e+08 | U88: 0 | V88: 0 | W88: 68619474 | X88: 80056053 | Y88: 0 | Z88: 34309737 | AA88: 2.7104692e+09 | AB88: 46007 | AC88: 0 | AI88: 0 | AJ88: 0 | AK88: N/A
A89: 00-177 | B89: EDIFICIOS PUERTO NIZUC FIDEICOMISO | C89: Edificios 7 y 8 - Puerto Nizuc | D89: Edificios 7 a 8 | E89: 1 | F89: Redet. Provisorio Nº 1 Cap Nº 1 Dic'25 | G89: Redet. | H89: 45992 | I89: 41089360 | J89: 41089360 | K89: 0 | L89: Validado | M89: FC A | N89: 2615 | O89: 46162 | P89: Certificado Redeterminado Provisorio Nº 1 - Cap Nº 1 Dic'25 | Q89: NO | R89: N/A | S89: 41089360 | T89: 4314382.8 | U89: 0 | V89: 0 | W89: 1232680.8 | X89: 1438127.6 | Y89: 0 | Z89: 616340.4 | AA89: 48690892 | AB89: 46007 | AC89: 0 | AI89: 0 | AJ89: 0 | AK89: N/A
A90: 00-177 | B90: EDIFICIOS PUERTO NIZUC FIDEICOMISO | C90: Edificios 7 y 8 - Puerto Nizuc | D90: Edificios 7 a 8 | E90: 2 | F90: Básico Nº 2 Cap 1 Ene'26 + CyC Nº 2 Cap 2-31 Ene'26 | G90: Básico | H90: 46023 | I90: 1.4720306e+09 | J90: 1.4720306e+09 | K90: 0 | L90: Validado | M90: FC A | N90: 2616 | O90: 46162 | P90: Certificado Básico Nº 2 - Cap 1 - Ene'26 / Costes y Costas Nº 2 - Cap 2-31 - Ene'26 | Q90: NO | R90: N/A | S90: 1.4720306e+09 | T90: 1.5456321e+08 | U90: 0 | V90: 0 | W90: 44160917 | X90: 51521069 | Y90: 0 | Z90: 22080458 | AA90: 1.7443562e+09 | AB90: 46007 | AC90: 0 | AI90: 0 | AJ90: 0 | AK90: N/A
A91: 00-177 | B91: EDIFICIOS PUERTO NIZUC FIDEICOMISO | C91: Edificios 7 y 8 - Puerto Nizuc | D91: Edificios 7 a 8 | E91: 2 | F91: Redet. Prov. Nº 2 Cap Nº 1 Ene'26 + Redet. Def. Nº 1 Cap Nº 1 Dic'25 | G91: Redet. | H91: 46023 | I91: 72697073 | J91: 72697073 | K91: 0 | L91: Validado | M91: FC A | N91: 2617 | O91: 46162 | P91: Certificado Redet. Provisorio Nº 2 - Cap Nº 1 Ene'26 / Redet. Definitivo Nº 1 - Cap Nº 1 Dic'25 | Q91: NO | R91: N/A | S91: 72697073 | T91: 7633192.7 | U91: 0 | V91: 0 | W91: 2180912.2 | X91: 2544397.6 | Y91: 0 | Z91: 1090456.1 | AA91: 86146032 | AB91: 46007 | AC91: 0 | AI91: 0 | AJ91: 0 | AK91: N/A
A92: 00-177 | B92: EDIFICIOS PUERTO NIZUC FIDEICOMISO | C92: Edificios 7 y 8 - Puerto Nizuc | D92: Edificios 7 a 8 | E92: 3 | F92: Básico Nº 3 Cap 1 Feb'26 + CyC Nº 3 Cap 2-31 Feb'26 | G92: Básico | H92: 46054 | I92: 8.0923548e+08 | J92: 8.0923548e+08 | K92: 0 | L92: Validado | M92: FC A | N92: 2618 | O92: 46162 | P92: Certificado Básico Nº 3 - Cap 1 - Feb'26 / Costes y Costas Nº 3 - Cap 2-31 - Feb'26 | Q92: NO | R92: N/A | S92: 8.0923548e+08 | T92: 84969725 | U92: 0 | V92: 0 | W92: 24277064 | X92: 28323242 | Y92: 0 | Z92: 12138532 | AA92: 9.5894404e+08 | AB92: 46007 | AC92: 0 | AI92: 0 | AJ92: 0 | AK92: N/A
A93: 00-177 | B93: EDIFICIOS PUERTO NIZUC FIDEICOMISO | C93: Edificios 7 y 8 - Puerto Nizuc | D93: Edificios 7 a 8 | E93: 3 | F93: Redet. Prov. Nº 3 Cap Nº 1 Feb'26 + Redet. Def. Nº 2 Cap Nº 1 Ene'26 | G93: Redet. | H93: 46054 | I93: 50219658 | J93: 50219658 | K93: 0 | L93: Validado | M93: FC A | N93: 2619 | O93: 46162 | P93: Certificado Redet. Provisorio Nº 3 - Cap Nº 1 Feb'26 / Redet. Definitivo Nº 2 - Cap Nº 1 Ene'26 | Q93: NO | R93: N/A | S93: 50219658 | T93: 5273064 | U93: 0 | V93: 0 | W93: 1506589.7 | X93: 1757688 | Y93: 0 | Z93: 753294.86 | AA93: 59510294 | AB93: 46007 | AC93: 0 | AI93: 0 | AJ93: 0 | AK93: N/A
A94: 00-177 | B94: EDIFICIOS PUERTO NIZUC FIDEICOMISO | C94: Edificios 7 y 8 - Puerto Nizuc | D94: Edificios 7 a 8 | E94: 4 | F94: Básico Nº 4 Cap 1 Mar'26 + CyC Nº 4 Cap 2-31 Mar'26 + Dev. Anticipo Financiero | G94: Básico | H94: 46082 | I94: =+J94-K94 | J94: 7.4074392e+08 | K94: 3.9905766e+08 | L94: Validado | M94: FC A | N94: 2620 | O94: 46162 | P94: Certificado Básico Nº 4 - Cap 1 - Mar'26 / Costes y Costas Nº 4 - Cap 2-31 - Mar'26 / Dev. Anticipo Financiero | Q94: NO | R94: N/A | S94: 3.9905766e+08 | T94: 41901054 | U94: 0 | V94: 0 | W94: 11971730 | X94: 13967018 | Y94: 0 | Z94: 5985864.8 | AA94: 4.7288332e+08 | AB94: 46164 | AC94: 3.9834246e+08 | AI94: =+AC94 | AJ94: =+AA94-AI94-AI95 | AK94: N/A
A95: 00-177 | B95: EDIFICIOS PUERTO NIZUC FIDEICOMISO | C95: Edificios 7 y 8 - Puerto Nizuc | D95: Edificios 7 a 8 | E95: 4 | F95: Redet. Prov. Nº 4 Cap Nº 1 Mar'26 + Redet. Def. Nº 3 Cap Nº 1 Feb'26 | G95: Redet. | H95: 46082 | I95: 26342888 | J95: 26342888 | K95: 0 | L95: Validado | M95: FC A | N95: 2621 | O95: 46162 | P95: Certificado Redet. Provisorio Nº 4 - Cap Nº 1 Mar'26 / Redet. Definitivo Nº 3 - Cap Nº 1 Feb'26 | Q95: NO | R95: N/A | S95: 26342888 | T95: 2766003.2 | U95: 0 | V95: 0 | W95: 790286.63 | X95: 922001.07 | Y95: 0 | Z95: 395143.32 | AA95: 31216322 | AB95: 46164 | AC95: 31216322 | AI95: =+AC95 | AJ95: 0 | AK95: =IF(Q95="ANULADA","N/A",IF(ABS(AJ95)>10,"Pendiente",IF(MAX(AB95,AD95,AF95)=0,"Pendiente",MAX(0,MAX(AB95,AD95,AF95)-O95))))
A96: 00-177 | B96: EDIFICIOS PUERTO NIZUC FIDEICOMISO | C96: Edificios 7 y 8 - Puerto Nizuc | D96: Edificios 7 a 8 | E96: NA | G96: Básico | H96: NA | K96: =+J96-I96 | M96: FC A | N96: 2623 | O96: 46178 | P96: Certificado Básico Nº 5 - Capitulo 1 - Abr'26.+Certificado Costes y Costas Nº 5 - Capitulo 2-31 - Abr'26. | Q96: ANULADA | R96: 637 | S96: 0 | T96: =0.105*S96 | U96: 0 | V96: =+S96*1.5% | W96: =+S96*3% | X96: =+S96*3.5% | AA96: =+S96+T96+U96+W96+X96+V96+Y96 | AI96: =+AC96+AE96+AG96+AH96 | AJ96: =+AA96-AI96 | AK96: N/A
A97: 00-177 | B97: EDIFICIOS PUERTO NIZUC FIDEICOMISO | C97: Edificios 7 y 8 - Puerto Nizuc | D97: Edificios 7 a 8 | E97: 5 | F97: Básico Nº 4 Abril'26 | G97: Básico | H97: 46113 | I97: 5343054.2 | J97: 1.1294309e+09 | K97: =+J97-I97 | L97: Validado | M97: FC A | N97: 2624 | O97: 46178 | P97: Certificado Básico Nº 5 - Capitulo 1 - Abr'26.+Certificado Costes y Costas Nº 5 - Capitulo 2-31 - Abr'26. | Q97: NO | R97: N/A | S97: =+K97 | T97: =0.105*S97 | U97: 0 | V97: =+S97*1.5% | W97: =+S97*3% | X97: =+S97*3.5% | AA97: =+S97+T97+U97+W97+X97+V97+Y97 | AI97: =+AC97+AE97+AG97+AH97 | AJ97: =+AA97-AI97 | AK97: =IF(Q97="ANULADA","N/A",IF(ABS(AJ97)>10,"Pendiente",IF(MAX(AB97,AD97,AF97)=0,"Pendiente",MAX(0,MAX(AB97,AD97,AF97)-O97))))
A98: 00-177 | B98: EDIFICIOS PUERTO NIZUC FIDEICOMISO | C98: Edificios 7 y 8 - Puerto Nizuc | D98: Edificios 7 a 8 | E98: 5 | F98: Redet Nº 4 Abril'26 | G98: Redet. | H98: 46113 | J98: 33310575 | K98: 33310575 | L98: Validado | M98: FC A | N98: 2625 | O98: 46178 | P98: Redeterminado Provisorio Nº 5 - Capitulo N° 1 Abr'26. + Redeterminado Definivo Nº 4 - Capitulo N° 1 Mar'26. | Q98: NO | R98: N/A | S98: =+K98 | T98: =0.105*S98 | V98: =+S98*1.5% | W98: =+S98*3% | X98: =+S98*3.5% | AA98: =+S98+T98+U98+W98+X98+V98+Y98 | AI98: =+AC98+AE98+AG98+AH98 | AJ98: =+AA98-AI98 | AK98: =IF(Q98="ANULADA","N/A",IF(ABS(AJ98)>10,"Pendiente",IF(MAX(AB98,AD98,AF98)=0,"Pendiente",MAX(0,MAX(AB98,AD98,AF98)-O98))))
A99: 00-177 | B99: EDIFICIOS PUERTO NIZUC FIDEICOMISO | C99: Edificios 7 y 8 - Puerto Nizuc | D99: Edificios 7 a 8 | E99: 6 | F99: Básico Nº 5 Mayo'26 | G99: Básico | H99: 46143 | J99: 1.0025707e+09 | K99: =+J99 | L99: En Espera | U99: =+S99*21% | V99: =+S99*3% | W99: =+S99*2.5% | X99: =IF(A99="00-175",S99*0.06,0) | AA99: =+S99+T99+U99+W99+X99+V99+Y99 | AI99: =+AC99+AE99+AG99+AH99 | AJ99: =+AA99-AI99 | AK99: =IF(Q99="ANULADA","N/A",IF(ABS(AJ99)>10,"Pendiente",IF(MAX(AB99,AD99,AF99)=0,"Pendiente",MAX(0,MAX(AB99,AD99,AF99)-O99))))
A100: 00-177 | B100: EDIFICIOS PUERTO NIZUC FIDEICOMISO | C100: Edificios 7 y 8 - Puerto Nizuc | D100: Edificios 7 a 8 | E100: 6 | F100: Redet Nº 5 Mayo'26 | G100: Redet. | H100: 46143 | J100: 49731814 | K100: =+J100 | L100: En Espera | U100: =+S100*21% | V100: =+S100*3% | W100: =+S100*2.5% | X100: =IF(A100="00-175",S100*0.06,0) | AA100: =+S100+T100+U100+W100+X100+V100+Y100 | AI100: =+AC100+AE100+AG100+AH100 | AJ100: =+AA100-AI100 | AK100: =IF(Q100="ANULADA","N/A",IF(ABS(AJ100)>10,"Pendiente",IF(MAX(AB100,AD100,AF100)=0,"Pendiente",MAX(0,MAX(AB100,AD100,AF100)-O100))))
A101: 00-178 | B101: EDIFICIOS PUERTO NIZUC FIDEICOMISO | C101: Edificio Oficinas - Puerto Nizuc | D101: Anticipo | F101: Anticipo | G101: Anticipo | H101: Anticipo | K101: 3.3906773e+09 | L101: Validado | M101: FC A | N101: 2555 | O101: 46022 | P101: Anticipo de Obra - Oficinas y 6 - Puerto Nizuc (00178) | Q101: NO | R101: N/A | S101: =+K101 | T101: =+S101*10.5% | W101: =+S101*3.5% | X101: =IF(A101="00-175",S101*0.06,0) | AA101: =+S101+T101+U101+W101+X101+V101+Y101 | AB101: 46022 | AC101: 3.8653721e+09 | AI101: =+AC101+AE101+AG101+AH101 | AJ101: =+AA101-AI101 | AK101: =IF(Q101="ANULADA","N/A",IF(ABS(AJ101)>10,"Pendiente",IF(MAX(AB101,AD101,AF101)=0,"Pendiente",MAX(0,MAX(AB101,AD101,AF101)-O101))))
A102: 00-178 | B102: EDIFICIOS PUERTO NIZUC FIDEICOMISO | C102: Edificio Oficinas - Puerto Nizuc | D102: Anticipo | F102: Anticipo | G102: Anticipo | H102: Anticipo | J102: 3.3906773e+09 | K102: 3.3906773e+09 | L102: Validado | M102: FC A | N102: 2580 | O102: 46053 | P102: Anticipo Financiero. - Edificio Oficinas - Puerto Nizuc (00178) | Q102: NO | R102: N/A | S102: =+J102 | U102: =+S102*21% | V102: 0 | W102: 0 | X102: =+S102*3.5% | AA102: =+S102+T102+U102+W102+X102+V102+Y102 | AI102: =+AC102+AE102+AG102+AH102 | AJ102: =+AA102-AI102 | AK102: =IF(Q102="ANULADA","N/A",IF(ABS(AJ102)>10,"Pendiente",IF(MAX(AB102,AD102,AF102)=0,"Pendiente",MAX(0,MAX(AB102,AD102,AF102)-O102))))
A103: 00-178 | B103: EDIFICIOS PUERTO NIZUC FIDEICOMISO | C103: Edificio Oficinas - Puerto Nizuc | D103: 6 y oficinas | E103: 1 | F103: Básico Nº 1 Oct-nov-dic | G103: Básico | H103: 45992 | I103: =+J103 | J103: 7.2973447e+08 | K103: 0 | L103: Validado | U103: =+S103*21% | V103: =+S103*3% | W103: =+S103*2.5% | X103: =IF(A103="00-175",S103*0.06,0) | AA103: =+S103+T103+U103+W103+X103+V103+Y103 | AI103: =+AC103+AE103+AG103+AH103 | AJ103: =+AA103-AI103 | AK103: N/A
A104: 00-178 | B104: EDIFICIOS PUERTO NIZUC FIDEICOMISO | C104: Edificio Oficinas - Puerto Nizuc | D104: 6 y oficinas | E104: 1 | F104: Redet Nº 1 Oct-nov-dic | G104: Redet. | H104: 45992 | I104: =+J104 | J104: 31374003 | K104: 0 | L104: Validado | U104: =+S104*21% | V104: =+S104*3% | W104: =+S104*2.5% | X104: =IF(A104="00-175",S104*0.06,0) | AA104: =+S104+T104+U104+W104+X104+V104+Y104 | AI104: =+AC104+AE104+AG104+AH104 | AJ104: =+AA104-AI104 | AK104: N/A
A105: 00-178 | B105: EDIFICIOS PUERTO NIZUC FIDEICOMISO | C105: Edificio Oficinas - Puerto Nizuc | D105: 6 y oficinas | E105: 2 | F105: Básico Nº 2 Enero 2026 | G105: Básico | H105: 46023 | I105: =+J105 | J105: 5.5769073e+08 | K105: 0 | L105: Validado | U105: =+S105*21% | V105: =+S105*3% | W105: =+S105*2.5% | X105: =IF(A105="00-175",S105*0.06,0) | AA105: =+S105+T105+U105+W105+X105+V105+Y105 | AI105: =+AC105+AE105+AG105+AH105 | AJ105: =+AA105-AI105 | AK105: N/A
...

Sheet 530 con Mora - Calc de int
A1: CÁLCULO DE INTERESES POR MORA — Cláusulas 14.7 / 14.8 FIDIC
A2: Interés = Monto × (Tasa+3%) × (Días mora / 365)
A4: Fuente | B4: https://www.bna.com.ar/home/informacionalusuariofinanciero
A5: Tasa anual de interés (Cl. 14.8) | B5: 0.249 | C5: ← TNA - Tasa Nominal Anual Vencida con capitalización cada 30 días = T.N.A. (30 días)
A6: Plazo contractual de pago (días) | B6: 60 | C6: ← Días desde emisión de la factura
A7: Fecha de corte | B7: =TODAY()
A9: N° Factura | B9: Fecha Certificado | C9: Fecha Emisión Factura | D9: Plazo Contractual (días) | E9: Fecha Venc. de Pago | F9: Fecha Pago Efectivo | G9: Días de Mora | H9: Monto Certificado y facturado ($) | I9: Tasa Anual de Interés + 3% | J9: Interés por Mora ($) | K9: Monto Total a Pagar ($)
A10: 1998 | B10: 46035 | C10: 46035 | D10: =$B$6 | E10: =C10+D10 | F10: ="" | G10: =IF(F10="",MAX(0,$B$7-E10),MAX(0,F10-E10)) | H10: 50402511 | I10: =$B$5+3% | J10: =H10*I10*(G10/365) | K10: =H10+J10
A11: 1999 | B11: 46035 | C11: 46035 | D11: =$B$6 | E11: =C11+D11 | F11: ="" | G11: =IF(F11="",MAX(0,$B$7-E11),MAX(0,F11-E11)) | H11: 677271.96 | I11: =$B$5+3% | J11: =H11*I11*(G11/365) | K11: =H11+J11
A12: 2000 | B12: 46035 | C12: 46035 | D12: =$B$6 | E12: =C12+D12 | F12: ="" | G12: =IF(F12="",MAX(0,$B$7-E12),MAX(0,F12-E12)) | H12: 17699825 | I12: =$B$5+3% | J12: =H12*I12*(G12/365) | K12: =H12+J12
A13: 2001 | B13: 46035 | C13: 46035 | D13: =$B$6 | E13: =C13+D13 | F13: ="" | G13: =IF(F13="",MAX(0,$B$7-E13),MAX(0,F13-E13)) | H13: 1015907.9 | I13: =$B$5+3% | J13: =H13*I13*(G13/365) | K13: =H13+J13
A14: 2002 | B14: 46035 | C14: 46035 | D14: =$B$6 | E14: =C14+D14 | F14: ="" | G14: =IF(F14="",MAX(0,$B$7-E14),MAX(0,F14-E14)) | H14: 27253875 | I14: =$B$5+3% | J14: =H14*I14*(G14/365) | K14: =H14+J14
A15: 2003 | B15: 46035 | C15: 46035 | D15: =$B$6 | E15: =C15+D15 | F15: ="" | G15: =IF(F15="",MAX(0,$B$7-E15),MAX(0,F15-E15)) | H15: 1015907.9 | I15: =$B$5+3% | J15: =H15*I15*(G15/365) | K15: =H15+J15
A16: 2004 | B16: 46035 | C16: 46035 | D16: =$B$6 | E16: =C16+D16 | F16: ="" | G16: =IF(F16="",MAX(0,$B$7-E16),MAX(0,F16-E16)) | H16: 28627721 | I16: =$B$5+3% | J16: =H16*I16*(G16/365) | K16: =H16+J16
A17: 2005 | B17: 46035 | C17: 46035 | D17: =$B$6 | E17: =C17+D17 | F17: ="" | G17: =IF(F17="",MAX(0,$B$7-E17),MAX(0,F17-E17)) | H17: 238400.46 | I17: =$B$5+3% | J17: =H17*I17*(G17/365) | K17: =H17+J17
A18: 2006 | B18: 46035 | C18: 46035 | D18: =$B$6 | E18: =C18+D18 | F18: ="" | G18: =IF(F18="",MAX(0,$B$7-E18),MAX(0,F18-E18)) | H18: 6758414.6 | I18: =$B$5+3% | J18: =H18*I18*(G18/365) | K18: =H18+J18
A19: 2008 | B19: 46051 | C19: 46051 | D19: =$B$6 | E19: =C19+D19 | F19: ="" | G19: =IF(F19="",MAX(0,$B$7-E19),MAX(0,F19-E19)) | H19: 444448.23 | I19: =$B$5+3% | J19: =H19*I19*(G19/365) | K19: =H19+J19
A20: 2010 | B20: 46051 | C20: 46051 | D20: =$B$6 | E20: =C20+D20 | F20: ="" | G20: =IF(F20="",MAX(0,$B$7-E20),MAX(0,F20-E20)) | H20: 12832109 | I20: =$B$5+3% | J20: =H20*I20*(G20/365) | K20: =H20+J20
A21: 2011 | B21: 46056 | C21: 46056 | D21: =$B$6 | E21: =C21+D21 | F21: ="" | G21: =IF(F21="",MAX(0,$B$7-E21),MAX(0,F21-E21)) | H21: 184056.25 | I21: =$B$5+3% | J21: =H21*I21*(G21/365) | K21: =H21+J21
... A31: 2024 | B31: 46142 | C31: 46142 | D31: =$B$6 | E31: =C31+D31 | F31: ="" | G31: =IF(F31="",MAX(0,$B$7-E31),MAX(0,F31-E31)) | H31: 1.315933e+08 | I31: =$B$5+3% | J31: =H31*I31*(G31/365) | K31: =H31+J31
A32: TOTAL | G32: =IF(COUNTA(F10:F31)>0,AVERAGE(G10:G31),AVERAGE(G10:G31)) | H32: =SUBTOTAL(109,H10:H31) | J32: =SUBTOTAL(109,J10:J31) | K32: =SUBTOTAL(109,K10:K31)
A34: RESUMEN
A35: Total Monto Certificados | B35: =H32
A36: Total Interés por Mora (Cl. 14.8) | B36: =J32
A37: Total a Reclamar | B37: =B35+B36
A38: Certificados en mora | B38: =COUNTIF(G10:G31,">"&0)
A39: Demora promedio (días) | B39: =G32

Sheet Anticipos
A1: UOP | B1: Descripción UOP | C1: Tipo Anticipo | D1: Nro Anticipo | E1: Factura | F1: Fecha Desembolso | G1: Monto Original ($) | H1: Con actualizacion | I1: Total Desacopiado ($) | J1: Saldo Pendiente ($) | K1: % Desacopiado
A2: 00-181 | B2: Bombeo Planta Potabilizadora Puerto Nizuc | C2: Anticipo Financiero 1 | D2: 1 | E2: 0018-00002514 | F2: 45938 | G2: 21615296 | I2: =SUMIFS(Master!I:I,Master!D:D,"Provision Tableros electricos") | J2: =G2-I2 | K2: =IFERROR(I2/G2,0)
A3: 00-181 | B3: Bombeo Planta Potabilizadora Puerto Nizuc | C3: Anticipo Cableado | D3: 2 | E3: 0018-00002548 | F3: 46078 | G3: 48893832 | I3: =SUMIFS(Master!I:I,Master!D:D,"Conexión y Cableado") | J3: =G3-I3 | K3: =IFERROR(I3/G3,0)
A4: 00-181 | B4: Bombeo Planta Potabilizadora Puerto Nizuc | C4: Anticipo Manifold y tableros | D4: 3 | E4: 0018-00002498 | F4: 45904 | G4: 81685880 | I4: =SUMIFS(Master!I:I,Master!D:D,"Manifold y Tableros") | J4: =G4-I4 | K4: =IFERROR(I4/G4,0)
A5: 00-181 | B5: Bombeo Planta Potabilizadora Puerto Nizuc | C5: Anticipo Bombeo Planta | D5: 4 | E5: 0018-00002503 | F5: 45916 | G5: 12601653 | I5: =SUMIFS(Master!I:I,Master!D:D,"Oficina Tecnica") | J5: =G5-I5 | K5: =IFERROR(I5/G5,0)
A6: 00-530 | B6: Redes y Colectores Cloacales Alderetes - Tucumán | C6: Anticipo Financiero | D6: 1 | E6: 0018-00001365 | F6: 44308 | G6: 1.7596957e+08 | I6: =SUMIFS(Master!I:I,Master!A:A,A6) | J6: =G6-I6 | K6: =IFERROR(I6/G6,0)
A7: 00-178 | B7: Edificio Oficinas - Puerto Nizuc | C7: Anticipo Financiero | D7: 1 | E7: 0018-00002555 | F7: 46007 | G7: 3.3906773e+09 | H7: =+G7*1.044428 | I7: =SUMIFS(Master!I:I,Master!A:A,A7) | J7: =H7-I7 | K7: =IFERROR(I7/H7,0)
A8: 00-177 | B8: Edificios 7 y 8 - Puerto Nizuc | C8: Anticipo Financiero | D8: 1 | E8: 0018-00002546 | F8: 46007 | G8: 4.8370062e+09 | H8: =+I8 | I8: =SUMIFS(Master!I:I,Master!A:A,A8) | J8: =H8-I8 | K8: =IFERROR(I8/H8,0)

Sheet Montos contractuales
A2: UOP | B2: Concepto | C2: Monto | D2: Fecha
A3: 00-530 | B3: contrato Ajuste alzado | C3: 1.7596957e+09 | D3: 44256
A4: 00-530 | B4: Ampliacion | C4: 3.5193462e+08 | D4: 46042
A5: 00-175 | B5: Carta Oferta | C5: 2.3370562e+09 | D5: 45870
A6: 00-176 | B6: Carta Oferta | C6: 5000000000 | D6: 46113
A7: 00-177 | B7: Contrato Coste y Costas | C7: 3.0896494e+10 | D7: 45870
A8: 00-178 | B8: Contrato Coste y Costas | C8: 3.3906773e+10 | D8: 45870
A9: 00-636 | B9: Carta Oferta | C9: 1500000000 | D9: 45839
